Workbook

Sheet Kedge P&L, Burn & Runway
A1: Kedge P&L, Burn & Runway
A2: Operating Model · Stress: Sonnet on big repos
A4: Variable / dimension | B4: 2026-10 | C4: 2026-11 | D4: 2026-12 | E4: 2027-01 | F4: 2027-02 | G4: 2027-03 | H4: 2027-04 | I4: 2027-05 | J4: 2027-06 | K4: 2027-07 | L4: 2027-08 | M4: 2027-09 | N4: 2027-10 | O4: 2027-11 | P4: 2027-12 | Q4: 2028-01 | R4: 2028-02 | S4: 2028-03 | T4: 2028-04 | U4: 2028-05 | V4: 2028-06 | W4: 2028-07 | X4: 2028-08 | Y4: 2028-09
A5: Revenue | B5: ='Model inputs'!C16*'Model inputs'!AA25 -> 600 | C5: ='Model inputs'!D16*'Model inputs'!AA25 -> 1090.9091 | D5: ='Model inputs'!E16*'Model inputs'!AA25 -> 1581.8182 | E5: ='Model inputs'!F16*'Model inputs'!AA25 -> 2072.7273 | F5: ='Model inputs'!G16*'Model inputs'!AA25 -> 2563.6364 | G5: ='Model inputs'!H16*'Model inputs'!AA25 -> 3054.5455 | H5: ='Model inputs'!I16*'Model inputs'!AA25 -> 3545.4545 | I5: ='Model inputs'!J16*'Model inputs'!AA25 -> 4036.3636 | J5: ='Model inputs'!K16*'Model inputs'!AA25 -> 4527.2727 | K5: ='Model inputs'!L16*'Model inputs'!AA25 -> 5018.1818 | L5: ='Model inputs'!M16*'Model inputs'!AA25 -> 5509.0909 | M5: ='Model inputs'!N16*'Model inputs'!AA25 -> 6000 | N5: ='Model inputs'!O16*'Model inputs'!AA25 -> 6000 | O5: ='Model inputs'!P16*'Model inputs'!AA25 -> 6000 | P5: ='Model inputs'!Q16*'Model inputs'!AA25 -> 6000 | Q5: ='Model inputs'!R16*'Model inputs'!AA25 -> 6000 | R5: ='Model inputs'!S16*'Model inputs'!AA25 -> 6000 | S5: ='Model inputs'!T16*'Model inputs'!AA25 -> 6000 | T5: ='Model inputs'!U16*'Model inputs'!AA25 -> 6000 | U5: ='Model inputs'!V16*'Model inputs'!AA25 -> 6000 | V5: ='Model inputs'!W16*'Model inputs'!AA25 -> 6000 | W5: ='Model inputs'!X16*'Model inputs'!AA25 -> 6000 | X5: ='Model inputs'!Y16*'Model inputs'!AA25 -> 6000 | Y5: ='Model inputs'!Z16*'Model inputs'!AA25 -> 6000
A6: AI model costs | B6: ='Model inputs'!C16*'Model inputs'!AA18 -> 171 | C6: ='Model inputs'!D16*'Model inputs'!AA18 -> 310.90909 | D6: ='Model inputs'!E16*'Model inputs'!AA18 -> 450.81818 | E6: ='Model inputs'!F16*'Model inputs'!AA18 -> 590.72727 | F6: ='Model inputs'!G16*'Model inputs'!AA18 -> 730.63636 | G6: ='Model inputs'!H16*'Model inputs'!AA18 -> 870.54545 | H6: ='Model inputs'!I16*'Model inputs'!AA18 -> 1010.4545 | I6: ='Model inputs'!J16*'Model inputs'!AA18 -> 1150.3636 | J6: ='Model inputs'!K16*'Model inputs'!AA18 -> 1290.2727 | K6: ='Model inputs'!L16*'Model inputs'!AA18 -> 1430.1818 | L6: ='Model inputs'!M16*'Model inputs'!AA18 -> 1570.0909 | M6: ='Model inputs'!N16*'Model inputs'!AA18 -> 1710 | N6: ='Model inputs'!O16*'Model inputs'!AA18 -> 1710 | O6: ='Model inputs'!P16*'Model inputs'!AA18 -> 1710 | P6: ='Model inputs'!Q16*'Model inputs'!AA18 -> 1710 | Q6: ='Model inputs'!R16*'Model inputs'!AA18 -> 1710 | R6: ='Model inputs'!S16*'Model inputs'!AA18 -> 1710 | S6: ='Model inputs'!T16*'Model inputs'!AA18 -> 1710 | T6: ='Model inputs'!U16*'Model inputs'!AA18 -> 1710 | U6: ='Model inputs'!V16*'Model inputs'!AA18 -> 1710 | V6: ='Model inputs'!W16*'Model inputs'!AA18 -> 1710 | W6: ='Model inputs'!X16*'Model inputs'!AA18 -> 1710 | X6: ='Model inputs'!Y16*'Model inputs'!AA18 -> 1710 | Y6: ='Model inputs'!Z16*'Model inputs'!AA18 -> 1710
A7: Payment processing | B7: ='Kedge P&L, Burn & Runway'!B5*'Model inputs'!AA24 -> 18 | C7: ='Kedge P&L, Burn & Runway'!C5*'Model inputs'!AA24 -> 32.727273 | D7: ='Kedge P&L, Burn & Runway'!D5*'Model inputs'!AA24 -> 47.454545 | E7: ='Kedge P&L, Burn & Runway'!E5*'Model inputs'!AA24 -> 62.181818 | F7: ='Kedge P&L, Burn & Runway'!F5*'Model inputs'!AA24 -> 76.909091 | G7: ='Kedge P&L, Burn & Runway'!G5*'Model inputs'!AA24 -> 91.636364 | H7: ='Kedge P&L, Burn & Runway'!H5*'Model inputs'!AA24 -> 106.36364 | I7: ='Kedge P&L, Burn & Runway'!I5*'Model inputs'!AA24 -> 121.09091 | J7: ='Kedge P&L, Burn & Runway'!J5*'Model inputs'!AA24 -> 135.81818 | K7: ='Kedge P&L, Burn & Runway'!K5*'Model inputs'!AA24 -> 150.54545 | L7: ='Kedge P&L, Burn & Runway'!L5*'Model inputs'!AA24 -> 165.27273 | M7: ='Kedge P&L, Burn & Runway'!M5*'Model inputs'!AA24 -> 180 | N7: ='Kedge P&L, Burn & Runway'!N5*'Model inputs'!AA24 -> 180 | O7: ='Kedge P&L, Burn & Runway'!O5*'Model inputs'!AA24 -> 180 | P7: ='Kedge P&L, Burn & Runway'!P5*'Model inputs'!AA24 -> 180 | Q7: ='Kedge P&L, Burn & Runway'!Q5*'Model inputs'!AA24 -> 180 | R7: ='Kedge P&L, Burn & Runway'!R5*'Model inputs'!AA24 -> 180 | S7: ='Kedge P&L, Burn & Runway'!S5*'Model inputs'!AA24 -> 180 | T7: ='Kedge P&L, Burn & Runway'!T5*'Model inputs'!AA24 -> 180 | U7: ='Kedge P&L, Burn & Runway'!U5*'Model inputs'!AA24 -> 180 | V7: ='Kedge P&L, Burn & Runway'!V5*'Model inputs'!AA24 -> 180 | W7: ='Kedge P&L, Burn & Runway'!W5*'Model inputs'!AA24 -> 180 | X7: ='Kedge P&L, Burn & Runway'!X5*'Model inputs'!AA24 -> 180 | Y7: ='Kedge P&L, Burn & Runway'!Y5*'Model inputs'!AA24 -> 180
A8: Cost of goods sold | B8: ='Kedge P&L, Burn & Runway'!B6+'Kedge P&L, Burn & Runway'!B7 -> 189 | C8: ='Kedge P&L, Burn & Runway'!C6+'Kedge P&L, Burn & Runway'!C7 -> 343.63636 | D8: ='Kedge P&L, Burn & Runway'!D6+'Kedge P&L, Burn & Runway'!D7 -> 498.27273 | E8: ='Kedge P&L, Burn & Runway'!E6+'Kedge P&L, Burn & Runway'!E7 -> 652.90909 | F8: ='Kedge P&L, Burn & Runway'!F6+'Kedge P&L, Burn & Runway'!F7 -> 807.54545 | G8: ='Kedge P&L, Burn & Runway'!G6+'Kedge P&L, Burn & Runway'!G7 -> 962.18182 | H8: ='Kedge P&L, Burn & Runway'!H6+'Kedge P&L, Burn & Runway'!H7 -> 1116.8182 | I8: ='Kedge P&L, Burn & Runway'!I6+'Kedge P&L, Burn & Runway'!I7 -> 1271.4545 | ... Y8: ='Kedge P&L, Burn & Runway'!Y6+'Kedge P&L, Burn & Runway'!Y7 -> 1890
A9: Gross profit | B9: ='Kedge P&L, Burn & Runway'!B5-'Kedge P&L, Burn & Runway'!B8 -> 411 | C9: ='Kedge P&L, Burn & Runway'!C5-'Kedge P&L, Burn & Runway'!C8 -> 747.27273 | D9: ='Kedge P&L, Burn & Runway'!D5-'Kedge P&L, Burn & Runway'!D8 -> 1083.5455 | E9: ='Kedge P&L, Burn & Runway'!E5-'Kedge P&L, Burn & Runway'!E8 -> 1419.8182 | F9: ='Kedge P&L, Burn & Runway'!F5-'Kedge P&L, Burn & Runway'!F8 -> 1756.0909 | G9: ='Kedge P&L, Burn & Runway'!G5-'Kedge P&L, Burn & Runway'!G8 -> 2092.3636 | H9: ='Kedge P&L, Burn & Runway'!H5-'Kedge P&L, Burn & Runway'!H8 -> 2428.6364 | I9: ='Kedge P&L, Burn & Runway'!I5-'Kedge P&L, Burn & Runway'!I8 -> 2764.9091 | ... Y9: ='Kedge P&L, Burn & Runway'!Y5-'Kedge P&L, Burn & Runway'!Y8 -> 4110
A10: Gross margin | B10: =IFERROR('Kedge P&L, Burn & Runway'!B9/'Kedge P&L, Burn & Runway'!B5,"") -> 0.685 | C10: =IFERROR('Kedge P&L, Burn & Runway'!C9/'Kedge P&L, Burn & Runway'!C5,"") -> 0.685 | D10: =IFERROR('Kedge P&L, Burn & Runway'!D9/'Kedge P&L, Burn & Runway'!D5,"") -> 0.685 | E10: =IFERROR('Kedge P&L, Burn & Runway'!E9/'Kedge P&L, Burn & Runway'!E5,"") -> 0.685 | F10: =IFERROR('Kedge P&L, Burn & Runway'!F9/'Kedge P&L, Burn & Runway'!F5,"") -> 0.685 | G10: =IFERROR('Kedge P&L, Burn & Runway'!G9/'Kedge P&L, Burn & Runway'!G5,"") -> 0.685 | H10: =IFERROR('Kedge P&L, Burn & Runway'!H9/'Kedge P&L, Burn & Runway'!H5,"") -> 0.685 | I10: =IFERROR('Kedge P&L, Burn & Runway'!I9/'Kedge P&L, Burn & Runway'!I5,"") -> 0.685 | ... Y10: =IFERROR('Kedge P&L, Burn & Runway'!Y9/'Kedge P&L, Burn & Runway'!Y5,"") -> 0.685
A11: Founder salaries | B11: =IF(IF(IF(ISERROR('Model inputs'!C19>'Model inputs'!AA31),'Model inputs'!C19>'Model inputs'!AA31,IF(OR('Model inputs'!C19="",'Model inputs'!AA31=""),"",'Model inputs'!C19>'Model inputs'!AA31))="",FALSE,IF(ISERROR('Model inputs'!C19>'Model inputs'!AA31),'Model inputs'!C19>'Model inputs'!AA31,IF(OR('Model inputs'!C19="",'Model inputs'!AA31=""),"",'Model inputs'!C19>'Model inputs'!AA31))),'Model inputs'!AA13*'Model inputs'!AA11,0) -> 0 | C11: =IF(IF(IF(ISERROR('Model inputs'!D19>'Model inputs'!AA31),'Model inputs'!D19>'Model inputs'!AA31,IF(OR('Model inputs'!D19="",'Model inputs'!AA31=""),"",'Model inputs'!D19>'Model inputs'!AA31))="",FALSE,IF(ISERROR('Model inputs'!D19>'Model inputs'!AA31),'Model inputs'!D19>'Model inputs'!AA31,IF(OR('Model inputs'!D19="",'Model inputs'!AA31=""),"",'Model inputs'!D19>'Model inputs'!AA31))),'Model inputs'!AA13*'Model inputs'!AA11,0) -> 0 | D11: =IF(IF(IF(ISERROR('Model inputs'!E19>'Model inputs'!AA31),'Model inputs'!E19>'Model inputs'!AA31,IF(OR('Model inputs'!E19="",'Model inputs'!AA31=""),"",'Model inputs'!E19>'Model inputs'!AA31))="",FALSE,IF(ISERROR('Model inputs'!E19>'Model inputs'!AA31),'Model inputs'!E19>'Model inputs'!AA31,IF(OR('Model inputs'!E19="",'Model inputs'!AA31=""),"",'Model inputs'!E19>'Model inputs'!AA31))),'Model inputs'!AA13*'Model inputs'!AA11,0) -> 0 | E11: =IF(IF(IF(ISERROR('Model inputs'!F19>'Model inputs'!AA31),'Model inputs'!F19>'Model inputs'!AA31,IF(OR('Model inputs'!F19="",'Model inputs'!AA31=""),"",'Model inputs'!F19>'Model inputs'!AA31))="",FALSE,IF(ISERROR('Model inputs'!F19>'Model inputs'!AA31),'Model inputs'!F19>'Model inputs'!AA31,IF(OR('Model inputs'!F19="",'Model inputs'!AA31=""),"",'Model inputs'!F19>'Model inputs'!AA31))),'Model inputs'!AA13*'Model inputs'!AA11,0) -> 0 | F11: =IF(IF(IF(ISERROR('Model inputs'!G19>'Model inputs'!AA31),'Model inputs'!G19>'Model inputs'!AA31,IF(OR('Model inputs'!G19="",'Model inputs'!AA31=""),"",'Model inputs'!G19>'Model inputs'!AA31))="",FALSE,IF(ISERROR('Model inputs'!G19>'Model inputs'!AA31),'Model inputs'!G19>'Model inputs'!AA31,IF(OR('Model inputs'!G19="",'Model inputs'!AA31=""),"",'Model inputs'!G19>'Model inputs'!AA31))),'Model inputs'!AA13*'Model inputs'!AA11,0) -> 0 | G11: =IF(IF(IF(ISERROR('Model inputs'!H19>'Model inputs'!AA31),'Model inputs'!H19>'Model inputs'!AA31,IF(OR('Model inputs'!H19="",'Model inputs'!AA31=""),"",'Model inputs'!H19>'Model inputs'!AA31))="",FALSE,IF(ISERROR('Model inputs'!H19>'Model inputs'!AA31),'Model inputs'!H19>'Model inputs'!AA31,IF(OR('Model inputs'!H19="",'Model inputs'!AA31=""),"",'Model inputs'!H19>'Model inputs'!AA31))),'Model inputs'!AA13*'Model inputs'!AA11,0) -> 0 | H11: =IF(IF(IF(ISERROR('Model inputs'!I19>'Model inputs'!AA31),'Model inputs'!I19>'Model inputs'!AA31,IF(OR('Model inputs'!I19="",'Model inputs'!AA31=""),"",'Model inputs'!I19>'Model inputs'!AA31))="",FALSE,IF(ISERROR('Model inputs'!I19>'Model inputs'!AA31),'Model inputs'!I19>'Model inputs'!AA31,IF(OR('Model inputs'!I19="",'Model inputs'!AA31=""),"",'Model inputs'!I19>'Model inputs'!AA31))),'Model inputs'!AA13*'Model inputs'!AA11,0) -> 8000 | I11: =IF(IF(IF(ISERROR('Model inputs'!J19>'Model inputs'!AA31),'Model inputs'!J19>'Model inputs'!AA31,IF(OR('Model inputs'!J19="",'Model inputs'!AA31=""),"",'Model inputs'!J19>'Model inputs'!AA31))="",FALSE,IF(ISERROR('Model inputs'!J19>'Model inputs'!AA31),'Model inputs'!J19>'Model inputs'!AA31,IF(OR('Model inputs'!J19="",'Model inputs'!AA31=""),"",'Model inputs'!J19>'Model inputs'!AA31))),'Model inputs'!AA13*'Model inputs'!AA11,0) -> 8000 | J11: =IF(IF(IF(ISERROR('Model inputs'!K19>'Model inputs'!AA31),'Model inputs'!K19>'Model inputs'!AA31,IF(OR('Model inputs'!K19="",'Model inputs'!AA31=""),"",'Model inputs'!K19>'Model inputs'!AA31))="",FALSE,IF(ISERROR('Model inputs'!K19>'Model inputs'!AA31),'Model inputs'!K19>'Model inputs'!AA31,IF(OR('Model inputs'!K19="",'Model inputs'!AA31=""),"",'Model inputs'!K19>'Model inputs'!AA31))),'Model inputs'!AA13*'Model inputs'!AA11,0) -> 8000 | K11: =IF(IF(IF(ISERROR('Model inputs'!L19>'Model inputs'!AA31),'Model inputs'!L19>'Model inputs'!AA31,IF(OR('Model inputs'!L19="",'Model inputs'!AA31=""),"",'Model inputs'!L19>'Model inputs'!AA31))="",FALSE,IF(ISERROR('Model inputs'!L19>'Model inputs'!AA31),'Model inputs'!L19>'Model inputs'!AA31,IF(OR('Model inputs'!L19="",'Model inputs'!AA31=""),"",'Model inputs'!L19>'Model inputs'!AA31))),'Model inputs'!AA13*'Model inputs'!AA11,0) -> 8000 | L11: =IF(IF(IF(ISERROR('Model inputs'!M19>'Model inputs'!AA31),'Model inputs'!M19>'Model inputs'!AA31,IF(OR('Model inputs'!M19="",'Model inputs'!AA31=""),"",'Model inputs'!M19>'Model inputs'!AA31))="",FALSE,IF(ISERROR('Model inputs'!M19>'Model inputs'!AA31),'Model inputs'!M19>'Model inputs'!AA31,IF(OR('Model inputs'!M19="",'Model inputs'!AA31=""),"",'Model inputs'!M19>'Model inputs'!AA31))),'Model inputs'!AA13*'Model inputs'!AA11,0) -> 8000 | M11: =IF(IF(IF(ISERROR('Model inputs'!N19>'Model inputs'!AA31),'Model inputs'!N19>'Model inputs'!AA31,IF(OR('Model inputs'!N19="",'Model inputs'!AA31=""),"",'Model inputs'!N19>'Model inputs'!AA31))="",FALSE,IF(ISERROR('Model inputs'!N19>'Model inputs'!AA31),'Model inputs'!N19>'Model inputs'!AA31,IF(OR('Model inputs'!N19="",'Model inputs'!AA31=""),"",'Model inputs'!N19>'Model inputs'!AA31))),'Model inputs'!AA13*'Model inputs'!AA11,0) -> 8000 | N11: =IF(IF(IF(ISERROR('Model inputs'!O19>'Model inputs'!AA31),'Model inputs'!O19>'Model inputs'!AA31,IF(OR('Model inputs'!O19="",'Model inputs'!AA31=""),"",'Model inputs'!O19>'Model inputs'!AA31))="",FALSE,IF(ISERROR('Model inputs'!O19>'Model inputs'!AA31),'Model inputs'!O19>'Model inputs'!AA31,IF(OR('Model inputs'!O19="",'Model inputs'!AA31=""),"",'Model inputs'!O19>'Model inputs'!AA31))),'Model inputs'!AA13*'Model inputs'!AA11,0) -> 8000 | O11: =IF(IF(IF(ISERROR('Model inputs'!P19>'Model inputs'!AA31),'Model inputs'!P19>'Model inputs'!AA31,IF(OR('Model inputs'!P19="",'Model inputs'!AA31=""),"",'Model inputs'!P19>'Model inputs'!AA31))="",FALSE,IF(ISERROR('Model inputs'!P19>'Model inputs'!AA31),'Model inputs'!P19>'Model inputs'!AA31,IF(OR('Model inputs'!P19="",'Model inputs'!AA31=""),"",'Model inputs'!P19>'Model inputs'!AA31))),'Model inputs'!AA13*'Model inputs'!AA11,0) -> 8000 | P11: =IF(IF(IF(ISERROR('Model inputs'!Q19>'Model inputs'!AA31),'Model inputs'!Q19>'Model inputs'!AA31,IF(OR('Model inputs'!Q19="",'Model inputs'!AA31=""),"",'Model inputs'!Q19>'Model inputs'!AA31))="",FALSE,IF(ISERROR('Model inputs'!Q19>'Model inputs'!AA31),'Model inputs'!Q19>'Model inputs'!AA31,IF(OR('Model inputs'!Q19="",'Model inputs'!AA31=""),"",'Model inputs'!Q19>'Model inputs'!AA31))),'Model inputs'!AA13*'Model inputs'!AA11,0) -> 8000 | Q11: =IF(IF(IF(ISERROR('Model inputs'!R19>'Model inputs'!AA31),'Model inputs'!R19>'Model inputs'!AA31,IF(OR('Model inputs'!R19="",'Model inputs'!AA31=""),"",'Model inputs'!R19>'Model inputs'!AA31))="",FALSE,IF(ISERROR('Model inputs'!R19>'Model inputs'!AA31),'Model inputs'!R19>'Model inputs'!AA31,IF(OR('Model inputs'!R19="",'Model inputs'!AA31=""),"",'Model inputs'!R19>'Model inputs'!AA31))),'Model inputs'!AA13*'Model inputs'!AA11,0) -> 8000 | R11: =IF(IF(IF(ISERROR('Model inputs'!S19>'Model inputs'!AA31),'Model inputs'!S19>'Model inputs'!AA31,IF(OR('Model inputs'!S19="",'Model inputs'!AA31=""),"",'Model inputs'!S19>'Model inputs'!AA31))="",FALSE,IF(ISERROR('Model inputs'!S19>'Model inputs'!AA31),'Model inputs'!S19>'Model inputs'!AA31,IF(OR('Model inputs'!S19="",'Model inputs'!AA31=""),"",'Model inputs'!S19>'Model inputs'!AA31))),'Model inputs'!AA13*'Model inputs'!AA11,0) -> 8000 | S11: =IF(IF(IF(ISERROR('Model inputs'!T19>'Model inputs'!AA31),'Model inputs'!T19>'Model inputs'!AA31,IF(OR('Model inputs'!T19="",'Model inputs'!AA31=""),"",'Model inputs'!T19>'Model inputs'!AA31))="",FALSE,IF(ISERROR('Model inputs'!T19>'Model inputs'!AA31),'Model inputs'!T19>'Model inputs'!AA31,IF(OR('Model inputs'!T19="",'Model inputs'!AA31=""),"",'Model inputs'!T19>'Model inputs'!AA31))),'Model inputs'!AA13*'Model inputs'!AA11,0) -> 8000 | T11: =IF(IF(IF(ISERROR('Model inputs'!U19>'Model inputs'!AA31),'Model inputs'!U19>'Model inputs'!AA31,IF(OR('Model inputs'!U19="",'Model inputs'!AA31=""),"",'Model inputs'!U19>'Model inputs'!AA31))="",FALSE,IF(ISERROR('Model inputs'!U19>'Model inputs'!AA31),'Model inputs'!U19>'Model inputs'!AA31,IF(OR('Model inputs'!U19="",'Model inputs'!AA31=""),"",'Model inputs'!U19>'Model inputs'!AA31))),'Model inputs'!AA13*'Model inputs'!AA11,0) -> 8000 | U11: =IF(IF(IF(ISERROR('Model inputs'!V19>'Model inputs'!AA31),'Model inputs'!V19>'Model inputs'!AA31,IF(OR('Model inputs'!V19="",'Model inputs'!AA31=""),"",'Model inputs'!V19>'Model inputs'!AA31))="",FALSE,IF(ISERROR('Model inputs'!V19>'Model inputs'!AA31),'Model inputs'!V19>'Model inputs'!AA31,IF(OR('Model inputs'!V19="",'Model inputs'!AA31=""),"",'Model inputs'!V19>'Model inputs'!AA31))),'Model inputs'!AA13*'Model inputs'!AA11,0) -> 8000 | V11: =IF(IF(IF(ISERROR('Model inputs'!W19>'Model inputs'!AA31),'Model inputs'!W19>'Model inputs'!AA31,IF(OR('Model inputs'!W19="",'Model inputs'!AA31=""),"",'Model inputs'!W19>'Model inputs'!AA31))="",FALSE,IF(ISERROR('Model inputs'!W19>'Model inputs'!AA31),'Model inputs'!W19>'Model inputs'!AA31,IF(OR('Model inputs'!W19="",'Model inputs'!AA31=""),"",'Model inputs'!W19>'Model inputs'!AA31))),'Model inputs'!AA13*'Model inputs'!AA11,0) -> 8000 | W11: =IF(IF(IF(ISERROR('Model inputs'!X19>'Model inputs'!AA31),'Model inputs'!X19>'Model inputs'!AA31,IF(OR('Model inputs'!X19="",'Model inputs'!AA31=""),"",'Model inputs'!X19>'Model inputs'!AA31))="",FALSE,IF(ISERROR('Model inputs'!X19>'Model inputs'!AA31),'Model inputs'!X19>'Model inputs'!AA31,IF(OR('Model inputs'!X19="",'Model inputs'!AA31=""),"",'Model inputs'!X19>'Model inputs'!AA31))),'Model inputs'!AA13*'Model inputs'!AA11,0) -> 8000 | X11: =IF(IF(IF(ISERROR('Model inputs'!Y19>'Model inputs'!AA31),'Model inputs'!Y19>'Model inputs'!AA31,IF(OR('Model inputs'!Y19="",'Model inputs'!AA31=""),"",'Model inputs'!Y19>'Model inputs'!AA31))="",FALSE,IF(ISERROR('Model inputs'!Y19>'Model inputs'!AA31),'Model inputs'!Y19>'Model inputs'!AA31,IF(OR('Model inputs'!Y19="",'Model inputs'!AA31=""),"",'Model inputs'!Y19>'Model inputs'!AA31))),'Model inputs'!AA13*'Model inputs'!AA11,0) -> 8000 | Y11: =IF(IF(IF(ISERROR('Model inputs'!Z19>'Model inputs'!AA31),'Model inputs'!Z19>'Model inputs'!AA31,IF(OR('Model inputs'!Z19="",'Model inputs'!AA31=""),"",'Model inputs'!Z19>'Model inputs'!AA31))="",FALSE,IF(ISERROR('Model inputs'!Z19>'Model inputs'!AA31),'Model inputs'!Z19>'Model inputs'!AA31,IF(OR('Model inputs'!Z19="",'Model inputs'!AA31=""),"",'Model inputs'!Z19>'Model inputs'!AA31))),'Model inputs'!AA13*'Model inputs'!AA11,0) -> 8000
A12: Software and tools | B12: =IF('Model inputs'!AA29="","",'Model inputs'!AA29) -> 200 | C12: =IF('Model inputs'!AA29="","",'Model inputs'!AA29) -> 200 | D12: =IF('Model inputs'!AA29="","",'Model inputs'!AA29) -> 200 | E12: =IF('Model inputs'!AA29="","",'Model inputs'!AA29) -> 200 | F12: =IF('Model inputs'!AA29="","",'Model inputs'!AA29) -> 200 | G12: =IF('Model inputs'!AA29="","",'Model inputs'!AA29) -> 200 | H12: =IF('Model inputs'!AA29="","",'Model inputs'!AA29) -> 200 | I12: =IF('Model inputs'!AA29="","",'Model inputs'!AA29) -> 200 | J12: =IF('Model inputs'!AA29="","",'Model inputs'!AA29) -> 200 | K12: =IF('Model inputs'!AA29="","",'Model inputs'!AA29) -> 200 | L12: =IF('Model inputs'!AA29="","",'Model inputs'!AA29) -> 200 | M12: =IF('Model inputs'!AA29="","",'Model inputs'!AA29) -> 200 | N12: =IF('Model inputs'!AA29="","",'Model inputs'!AA29) -> 200 | O12: =IF('Model inputs'!AA29="","",'Model inputs'!AA29) -> 200 | P12: =IF('Model inputs'!AA29="","",'Model inputs'!AA29) -> 200 | Q12: =IF('Model inputs'!AA29="","",'Model inputs'!AA29) -> 200 | R12: =IF('Model inputs'!AA29="","",'Model inputs'!AA29) -> 200 | S12: =IF('Model inputs'!AA29="","",'Model inputs'!AA29) -> 200 | T12: =IF('Model inputs'!AA29="","",'Model inputs'!AA29) -> 200 | U12: =IF('Model inputs'!AA29="","",'Model inputs'!AA29) -> 200 | V12: =IF('Model inputs'!AA29="","",'Model inputs'!AA29) -> 200 | W12: =IF('Model inputs'!AA29="","",'Model inputs'!AA29) -> 200 | X12: =IF('Model inputs'!AA29="","",'Model inputs'!AA29) -> 200 | Y12: =IF('Model inputs'!AA29="","",'Model inputs'!AA29) -> 200
A13: Operating expenses | B13: ='Kedge P&L, Burn & Runway'!B11+'Kedge P&L, Burn & Runway'!B12 -> 200 | C13: ='Kedge P&L, Burn & Runway'!C11+'Kedge P&L, Burn & Runway'!C12 -> 200 | D13: ='Kedge P&L, Burn & Runway'!D11+'Kedge P&L, Burn & Runway'!D12 -> 200 | E13: ='Kedge P&L, Burn & Runway'!E11+'Kedge P&L, Burn & Runway'!E12 -> 200 | F13: ='Kedge P&L, Burn & Runway'!F11+'Kedge P&L, Burn & Runway'!F12 -> 200 | G13: ='Kedge P&L, Burn & Runway'!G11+'Kedge P&L, Burn & Runway'!G12 -> 200 | H13: ='Kedge P&L, Burn & Runway'!H11+'Kedge P&L, Burn & Runway'!H12 -> 8200 | I13: ='Kedge P&L, Burn & Runway'!I11+'Kedge P&L, Burn & Runway'!I12 -> 8200 | ... Y13: ='Kedge P&L, Burn & Runway'!Y11+'Kedge P&L, Burn & Runway'!Y12 -> 8200
A14: Operating income | B14: ='Kedge P&L, Burn & Runway'!B9-'Kedge P&L, Burn & Runway'!B13 -> 211 | C14: ='Kedge P&L, Burn & Runway'!C9-'Kedge P&L, Burn & Runway'!C13 -> 547.27273 | D14: ='Kedge P&L, Burn & Runway'!D9-'Kedge P&L, Burn & Runway'!D13 -> 883.54545 | E14: ='Kedge P&L, Burn & Runway'!E9-'Kedge P&L, Burn & Runway'!E13 -> 1219.8182 | F14: ='Kedge P&L, Burn & Runway'!F9-'Kedge P&L, Burn & Runway'!F13 -> 1556.0909 | G14: ='Kedge P&L, Burn & Runway'!G9-'Kedge P&L, Burn & Runway'!G13 -> 1892.3636 | H14: ='Kedge P&L, Burn & Runway'!H9-'Kedge P&L, Burn & Runway'!H13 -> -5771.3636 | I14: ='Kedge P&L, Burn & Runway'!I9-'Kedge P&L, Burn & Runway'!I13 -> -5435.0909 | ... Y14: ='Kedge P&L, Burn & Runway'!Y9-'Kedge P&L, Burn & Runway'!Y13 -> -4090
A15: Net burn | B15: =-'Kedge P&L, Burn & Runway'!B14 -> -211 | C15: =-'Kedge P&L, Burn & Runway'!C14 -> -547.27273 | D15: =-'Kedge P&L, Burn & Runway'!D14 -> -883.54545 | E15: =-'Kedge P&L, Burn & Runway'!E14 -> -1219.8182 | F15: =-'Kedge P&L, Burn & Runway'!F14 -> -1556.0909 | G15: =-'Kedge P&L, Burn & Runway'!G14 -> -1892.3636 | H15: =-'Kedge P&L, Burn & Runway'!H14 -> 5771.3636 | I15: =-'Kedge P&L, Burn & Runway'!I14 -> 5435.0909 | ... Y15: =-'Kedge P&L, Burn & Runway'!Y14 -> 4090
A16: Equity raised | B16: 0 | C16: 0 | D16: 0 | E16: 0 | F16: 0 | G16: 0 | H16: =60000 -> 60000 | I16: 0 | J16: 0 | K16: 0 | L16: 0 | M16: 0 | N16: 0 | O16: 0 | P16: 0 | Q16: 0 | R16: 0 | S16: 0 | T16: 0 | U16: 0 | V16: 0 | W16: 0 | X16: 0 | Y16: 0
A17: Cash balance | B17: ='Model inputs'!B7-'Kedge P&L, Burn & Runway'!B15+'Kedge P&L, Burn & Runway'!B16 -> 211 | C17: ='Kedge P&L, Burn & Runway'!B17-'Kedge P&L, Burn & Runway'!C15+'Kedge P&L, Burn & Runway'!C16 -> 758.27273 | D17: ='Kedge P&L, Burn & Runway'!C17-'Kedge P&L, Burn & Runway'!D15+'Kedge P&L, Burn & Runway'!D16 -> 1641.8182 | E17: ='Kedge P&L, Burn & Runway'!D17-'Kedge P&L, Burn & Runway'!E15+'Kedge P&L, Burn & Runway'!E16 -> 2861.6364 | F17: ='Kedge P&L, Burn & Runway'!E17-'Kedge P&L, Burn & Runway'!F15+'Kedge P&L, Burn & Runway'!F16 -> 4417.7273 | G17: ='Kedge P&L, Burn & Runway'!F17-'Kedge P&L, Burn & Runway'!G15+'Kedge P&L, Burn & Runway'!G16 -> 6310.0909 | H17: ='Kedge P&L, Burn & Runway'!G17-'Kedge P&L, Burn & Runway'!H15+'Kedge P&L, Burn & Runway'!H16 -> 60538.727 | I17: ='Kedge P&L, Burn & Runway'!H17-'Kedge P&L, Burn & Runway'!I15+'Kedge P&L, Burn & Runway'!I16 -> 55103.636 | J17: ='Kedge P&L, Burn & Runway'!I17-'Kedge P&L, Burn & Runway'!J15+'Kedge P&L, Burn & Runway'!J16 -> 50004.818 | ... Y17: ='Kedge P&L, Burn & Runway'!X17-'Kedge P&L, Burn & Runway'!Y15+'Kedge P&L, Burn & Runway'!Y16 -> -12354
A18: Funding needed to date | B18: =IF(IF(IF(ISERROR(-'Kedge P&L, Burn & Runway'!B17>'Model inputs'!B14),-'Kedge P&L, Burn & Runway'!B17>'Model inputs'!B14,IF('Model inputs'!B14="","",-'Kedge P&L, Burn & Runway'!B17>'Model inputs'!B14))="",FALSE,IF(ISERROR(-'Kedge P&L, Burn & Runway'!B17>'Model inputs'!B14),-'Kedge P&L, Burn & Runway'!B17>'Model inputs'!B14,IF('Model inputs'!B14="","",-'Kedge P&L, Burn & Runway'!B17>'Model inputs'!B14))),-'Kedge P&L, Burn & Runway'!B17,IF('Model inputs'!B14="","",'Model inputs'!B14)) -> 0 | C18: =IF(IF(IF(ISERROR(-'Kedge P&L, Burn & Runway'!C17>'Kedge P&L, Burn & Runway'!B18),-'Kedge P&L, Burn & Runway'!C17>'Kedge P&L, Burn & Runway'!B18,IF('Kedge P&L, Burn & Runway'!B18="","",-'Kedge P&L, Burn & Runway'!C17>'Kedge P&L, Burn & Runway'!B18))="",FALSE,IF(ISERROR(-'Kedge P&L, Burn & Runway'!C17>'Kedge P&L, Burn & Runway'!B18),-'Kedge P&L, Burn & Runway'!C17>'Kedge P&L, Burn & Runway'!B18,IF('Kedge P&L, Burn & Runway'!B18="","",-'Kedge P&L, Burn & Runway'!C17>'Kedge P&L, Burn & Runway'!B18))),-'Kedge P&L, Burn & Runway'!C17,IF('Kedge P&L, Burn & Runway'!B18="","",'Kedge P&L, Burn & Runway'!B18)) -> 0 | D18: =IF(IF(IF(ISERROR(-'Kedge P&L, Burn & Runway'!D17>'Kedge P&L, Burn & Runway'!C18),-'Kedge P&L, Burn & Runway'!D17>'Kedge P&L, Burn & Runway'!C18,IF('Kedge P&L, Burn & Runway'!C18="","",-'Kedge P&L, Burn & Runway'!D17>'Kedge P&L, Burn & Runway'!C18))="",FALSE,IF(ISERROR(-'Kedge P&L, Burn & Runway'!D17>'Kedge P&L, Burn & Runway'!C18),-'Kedge P&L, Burn & Runway'!D17>'Kedge P&L, Burn & Runway'!C18,IF('Kedge P&L, Burn & Runway'!C18="","",-'Kedge P&L, Burn & Runway'!D17>'Kedge P&L, Burn & Runway'!C18))),-'Kedge P&L, Burn & Runway'!D17,IF('Kedge P&L, Burn & Runway'!C18="","",'Kedge P&L, Burn & Runway'!C18)) -> 0 | E18: =IF(IF(IF(ISERROR(-'Kedge P&L, Burn & Runway'!E17>'Kedge P&L, Burn & Runway'!D18),-'Kedge P&L, Burn & Runway'!E17>'Kedge P&L, Burn & Runway'!D18,IF('Kedge P&L, Burn & Runway'!D18="","",-'Kedge P&L, Burn & Runway'!E17>'Kedge P&L, Burn & Runway'!D18))="",FALSE,IF(ISERROR(-'Kedge P&L, Burn & Runway'!E17>'Kedge P&L, Burn & Runway'!D18),-'Kedge P&L, Burn & Runway'!E17>'Kedge P&L, Burn & Runway'!D18,IF('Kedge P&L, Burn & Runway'!D18="","",-'Kedge P&L, Burn & Runway'!E17>'Kedge P&L, Burn & Runway'!D18))),-'Kedge P&L, Burn & Runway'!E17,IF('Kedge P&L, Burn & Runway'!D18="","",'Kedge P&L, Burn & Runway'!D18)) -> 0 | F18: =IF(IF(IF(ISERROR(-'Kedge P&L, Burn & Runway'!F17>'Kedge P&L, Burn & Runway'!E18),-'Kedge P&L, Burn & Runway'!F17>'Kedge P&L, Burn & Runway'!E18,IF('Kedge P&L, Burn & Runway'!E18="","",-'Kedge P&L, Burn & Runway'!F17>'Kedge P&L, Burn & Runway'!E18))="",FALSE,IF(ISERROR(-'Kedge P&L, Burn & Runway'!F17>'Kedge P&L, Burn & Runway'!E18),-'Kedge P&L, Burn & Runway'!F17>'Kedge P&L, Burn & Runway'!E18,IF('Kedge P&L, Burn & Runway'!E18="","",-'Kedge P&L, Burn & Runway'!F17>'Kedge P&L, Burn & Runway'!E18))),-'Kedge P&L, Burn & Runway'!F17,IF('Kedge P&L, Burn & Runway'!E18="","",'Kedge P&L, Burn & Runway'!E18)) -> 0 | G18: =IF(IF(IF(ISERROR(-'Kedge P&L, Burn & Runway'!G17>'Kedge P&L, Burn & Runway'!F18),-'Kedge P&L, Burn & Runway'!G17>'Kedge P&L, Burn & Runway'!F18,IF('Kedge P&L, Burn & Runway'!F18="","",-'Kedge P&L, Burn & Runway'!G17>'Kedge P&L, Burn & Runway'!F18))="",FALSE,IF(ISERROR(-'Kedge P&L, Burn & Runway'!G17>'Kedge P&L, Burn & Runway'!F18),-'Kedge P&L, Burn & Runway'!G17>'Kedge P&L, Burn & Runway'!F18,IF('Kedge P&L, Burn & Runway'!F18="","",-'Kedge P&L, Burn & Runway'!G17>'Kedge P&L, Burn & Runway'!F18))),-'Kedge P&L, Burn & Runway'!G17,IF('Kedge P&L, Burn & Runway'!F18="","",'Kedge P&L, Burn & Runway'!F18)) -> 0 | H18: =IF(IF(IF(ISERROR(-'Kedge P&L, Burn & Runway'!H17>'Kedge P&L, Burn & Runway'!G18),-'Kedge P&L, Burn & Runway'!H17>'Kedge P&L, Burn & Runway'!G18,IF('Kedge P&L, Burn & Runway'!G18="","",-'Kedge P&L, Burn & Runway'!H17>'Kedge P&L, Burn & Runway'!G18))="",FALSE,IF(ISERROR(-'Kedge P&L, Burn & Runway'!H17>'Kedge P&L, Burn & Runway'!G18),-'Kedge P&L, Burn & Runway'!H17>'Kedge P&L, Burn & Runway'!G18,IF('Kedge P&L, Burn & Runway'!G18="","",-'Kedge P&L, Burn & Runway'!H17>'Kedge P&L, Burn & Runway'!G18))),-'Kedge P&L, Burn & Runway'!H17,IF('Kedge P&L, Burn & Runway'!G18="","",'Kedge P&L, Burn & Runway'!G18)) -> 0 | I18: =IF(IF(IF(ISERROR(-'Kedge P&L, Burn & Runway'!I17>'Kedge P&L, Burn & Runway'!H18),-'Kedge P&L, Burn & Runway'!I17>'Kedge P&L, Burn & Runway'!H18,IF('Kedge P&L, Burn & Runway'!H18="","",-'Kedge P&L, Burn & Runway'!I17>'Kedge P&L, Burn & Runway'!H18))="",FALSE,IF(ISERROR(-'Kedge P&L, Burn & Runway'!I17>'Kedge P&L, Burn & Runway'!H18),-'Kedge P&L, Burn & Runway'!I17>'Kedge P&L, Burn & Runway'!H18,IF('Kedge P&L, Burn & Runway'!H18="","",-'Kedge P&L, Burn & Runway'!I17>'Kedge P&L, Burn & Runway'!H18))),-'Kedge P&L, Burn & Runway'!I17,IF('Kedge P&L, Burn & Runway'!H18="","",'Kedge P&L, Burn & Runway'!H18)) -> 0 | J18: =IF(IF(IF(ISERROR(-'Kedge P&L, Burn & Runway'!J17>'Kedge P&L, Burn & Runway'!I18),-'Kedge P&L, Burn & Runway'!J17>'Kedge P&L, Burn & Runway'!I18,IF('Kedge P&L, Burn & Runway'!I18="","",-'Kedge P&L, Burn & Runway'!J17>'Kedge P&L, Burn & Runway'!I18))="",FALSE,IF(ISERROR(-'Kedge P&L, Burn & Runway'!J17>'Kedge P&L, Burn & Runway'!I18),-'Kedge P&L, Burn & Runway'!J17>'Kedge P&L, Burn & Runway'!I18,IF('Kedge P&L, Burn & Runway'!I18="","",-'Kedge P&L, Burn & Runway'!J17>'Kedge P&L, Burn & Runway'!I18))),-'Kedge P&L, Burn & Runway'!J17,IF('Kedge P&L, Burn & Runway'!I18="","",'Kedge P&L, Burn & Runway'!I18)) -> 0 | ... Y18: =IF(IF(IF(ISERROR(-'Kedge P&L, Burn & Runway'!Y17>'Kedge P&L, Burn & Runway'!X18),-'Kedge P&L, Burn & Runway'!Y17>'Kedge P&L, Burn & Runway'!X18,IF('Kedge P&L, Burn & Runway'!X18="","",-'Kedge P&L, Burn & Runway'!Y17>'Kedge P&L, Burn & Runway'!X18))="",FALSE,IF(ISERROR(-'Kedge P&L, Burn & Runway'!Y17>'Kedge P&L, Burn & Runway'!X18),-'Kedge P&L, Burn & Runway'!Y17>'Kedge P&L, Burn & Runway'!X18,IF('Kedge P&L, Burn & Runway'!X18="","",-'Kedge P&L, Burn & Runway'!Y17>'Kedge P&L, Burn & Runway'!X18))),-'Kedge P&L, Burn & Runway'!Y17,IF('Kedge P&L, Burn & Runway'!X18="","",'Kedge P&L, Burn & Runway'!X18)) -> 12354
A19: Runway (months) | B19: =IF(IF(IF(ISERROR('Kedge P&L, Burn & Runway'!B15>0),'Kedge P&L, Burn & Runway'!B15>0,IF('Kedge P&L, Burn & Runway'!B15="","",'Kedge P&L, Burn & Runway'!B15>0))="",FALSE,IF(ISERROR('Kedge P&L, Burn & Runway'!B15>0),'Kedge P&L, Burn & Runway'!B15>0,IF('Kedge P&L, Burn & Runway'!B15="","",'Kedge P&L, Burn & Runway'!B15>0))),IF(IF(IF(ISERROR('Kedge P&L, Burn & Runway'!B17>0),'Kedge P&L, Burn & Runway'!B17>0,IF('Kedge P&L, Burn & Runway'!B17="","",'Kedge P&L, Burn & Runway'!B17>0))="",FALSE,IF(ISERROR('Kedge P&L, Burn & Runway'!B17>0),'Kedge P&L, Burn & Runway'!B17>0,IF('Kedge P&L, Burn & Runway'!B17="","",'Kedge P&L, Burn & Runway'!B17>0))),'Kedge P&L, Burn & Runway'!B17/'Kedge P&L, Burn & Runway'!B15,0),"") | C19: =IF(IF(IF(ISERROR('Kedge P&L, Burn & Runway'!C15>0),'Kedge P&L, Burn & Runway'!C15>0,IF('Kedge P&L, Burn & Runway'!C15="","",'Kedge P&L, Burn & Runway'!C15>0))="",FALSE,IF(ISERROR('Kedge P&L, Burn & Runway'!C15>0),'Kedge P&L, Burn & Runway'!C15>0,IF('Kedge P&L, Burn & Runway'!C15="","",'Kedge P&L, Burn & Runway'!C15>0))),IF(IF(IF(ISERROR('Kedge P&L, Burn & Runway'!C17>0),'Kedge P&L, Burn & Runway'!C17>0,IF('Kedge P&L, Burn & Runway'!C17="","",'Kedge P&L, Burn & Runway'!C17>0))="",FALSE,IF(ISERROR('Kedge P&L, Burn & Runway'!C17>0),'Kedge P&L, Burn & Runway'!C17>0,IF('Kedge P&L, Burn & Runway'!C17="","",'Kedge P&L, Burn & Runway'!C17>0))),'Kedge P&L, Burn & Runway'!C17/'Kedge P&L, Burn & Runway'!C15,0),"") | D19: =IF(IF(IF(ISERROR('Kedge P&L, Burn & Runway'!D15>0),'Kedge P&L, Burn & Runway'!D15>0,IF('Kedge P&L, Burn & Runway'!D15="","",'Kedge P&L, Burn & Runway'!D15>0))="",FALSE,IF(ISERROR('Kedge P&L, Burn & Runway'!D15>0),'Kedge P&L, Burn & Runway'!D15>0,IF('Kedge P&L, Burn & Runway'!D15="","",'Kedge P&L, Burn & Runway'!D15>0))),IF(IF(IF(ISERROR('Kedge P&L, Burn & Runway'!D17>0),'Kedge P&L, Burn & Runway'!D17>0,IF('Kedge P&L, Burn & Runway'!D17="","",'Kedge P&L, Burn & Runway'!D17>0))="",FALSE,IF(ISERROR('Kedge P&L, Burn & Runway'!D17>0),'Kedge P&L, Burn & Runway'!D17>0,IF('Kedge P&L, Burn & Runway'!D17="","",'Kedge P&L, Burn & Runway'!D17>0))),'Kedge P&L, Burn & Runway'!D17/'Kedge P&L, Burn & Runway'!D15,0),"") | E19: =IF(IF(IF(ISERROR('Kedge P&L, Burn & Runway'!E15>0),'Kedge P&L, Burn & Runway'!E15>0,IF('Kedge P&L, Burn & Runway'!E15="","",'Kedge P&L, Burn & Runway'!E15>0))="",FALSE,IF(ISERROR('Kedge P&L, Burn & Runway'!E15>0),'Kedge P&L, Burn & Runway'!E15>0,IF('Kedge P&L, Burn & Runway'!E15="","",'Kedge P&L, Burn & Runway'!E15>0))),IF(IF(IF(ISERROR('Kedge P&L, Burn & Runway'!E17>0),'Kedge P&L, Burn & Runway'!E17>0,IF('Kedge P&L, Burn & Runway'!E17="","",'Kedge P&L, Burn & Runway'!E17>0))="",FALSE,IF(ISERROR('Kedge P&L, Burn & Runway'!E17>0),'Kedge P&L, Burn & Runway'!E17>0,IF('Kedge P&L, Burn & Runway'!E17="","",'Kedge P&L, Burn & Runway'!E17>0))),'Kedge P&L, Burn & Runway'!E17/'Kedge P&L, Burn & Runway'!E15,0),"") | F19: =IF(IF(IF(ISERROR('Kedge P&L, Burn & Runway'!F15>0),'Kedge P&L, Burn & Runway'!F15>0,IF('Kedge P&L, Burn & Runway'!F15="","",'Kedge P&L, Burn & Runway'!F15>0))="",FALSE,IF(ISERROR('Kedge P&L, Burn & Runway'!F15>0),'Kedge P&L, Burn & Runway'!F15>0,IF('Kedge P&L, Burn & Runway'!F15="","",'Kedge P&L, Burn & Runway'!F15>0))),IF(IF(IF(ISERROR('Kedge P&L, Burn & Runway'!F17>0),'Kedge P&L, Burn & Runway'!F17>0,IF('Kedge P&L, Burn & Runway'!F17="","",'Kedge P&L, Burn & Runway'!F17>0))="",FALSE,IF(ISERROR('Kedge P&L, Burn & Runway'!F17>0),'Kedge P&L, Burn & Runway'!F17>0,IF('Kedge P&L, Burn & Runway'!F17="","",'Kedge P&L, Burn & Runway'!F17>0))),'Kedge P&L, Burn & Runway'!F17/'Kedge P&L, Burn & Runway'!F15,0),"") | G19: =IF(IF(IF(ISERROR('Kedge P&L, Burn & Runway'!G15>0),'Kedge P&L, Burn & Runway'!G15>0,IF('Kedge P&L, Burn & Runway'!G15="","",'Kedge P&L, Burn & Runway'!G15>0))="",FALSE,IF(ISERROR('Kedge P&L, Burn & Runway'!G15>0),'Kedge P&L, Burn & Runway'!G15>0,IF('Kedge P&L, Burn & Runway'!G15="","",'Kedge P&L, Burn & Runway'!G15>0))),IF(IF(IF(ISERROR('Kedge P&L, Burn & Runway'!G17>0),'Kedge P&L, Burn & Runway'!G17>0,IF('Kedge P&L, Burn & Runway'!G17="","",'Kedge P&L, Burn & Runway'!G17>0))="",FALSE,IF(ISERROR('Kedge P&L, Burn & Runway'!G17>0),'Kedge P&L, Burn & Runway'!G17>0,IF('Kedge P&L, Burn & Runway'!G17="","",'Kedge P&L, Burn & Runway'!G17>0))),'Kedge P&L, Burn & Runway'!G17/'Kedge P&L, Burn & Runway'!G15,0),"") | H19: =IF(IF(IF(ISERROR('Kedge P&L, Burn & Runway'!H15>0),'Kedge P&L, Burn & Runway'!H15>0,IF('Kedge P&L, Burn & Runway'!H15="","",'Kedge P&L, Burn & Runway'!H15>0))="",FALSE,IF(ISERROR('Kedge P&L, Burn & Runway'!H15>0),'Kedge P&L, Burn & Runway'!H15>0,IF('Kedge P&L, Burn & Runway'!H15="","",'Kedge P&L, Burn & Runway'!H15>0))),IF(IF(IF(ISERROR('Kedge P&L, Burn & Runway'!H17>0),'Kedge P&L, Burn & Runway'!H17>0,IF('Kedge P&L, Burn & Runway'!H17="","",'Kedge P&L, Burn & Runway'!H17>0))="",FALSE,IF(ISERROR('Kedge P&L, Burn & Runway'!H17>0),'Kedge P&L, Burn & Runway'!H17>0,IF('Kedge P&L, Burn & Runway'!H17="","",'Kedge P&L, Burn & Runway'!H17>0))),'Kedge P&L, Burn & Runway'!H17/'Kedge P&L, Burn & Runway'!H15,0),"") -> 10.489501 | I19: =IF(IF(IF(ISERROR('Kedge P&L, Burn & Runway'!I15>0),'Kedge P&L, Burn & Runway'!I15>0,IF('Kedge P&L, Burn & Runway'!I15="","",'Kedge P&L, Burn & Runway'!I15>0))="",FALSE,IF(ISERROR('Kedge P&L, Burn & Runway'!I15>0),'Kedge P&L, Burn & Runway'!I15>0,IF('Kedge P&L, Burn & Runway'!I15="","",'Kedge P&L, Burn & Runway'!I15>0))),IF(IF(IF(ISERROR('Kedge P&L, Burn & Runway'!I17>0),'Kedge P&L, Burn & Runway'!I17>0,IF('Kedge P&L, Burn & Runway'!I17="","",'Kedge P&L, Burn & Runway'!I17>0))="",FALSE,IF(ISERROR('Kedge P&L, Burn & Runway'!I17>0),'Kedge P&L, Burn & Runway'!I17>0,IF('Kedge P&L, Burn & Runway'!I17="","",'Kedge P&L, Burn & Runway'!I17>0))),'Kedge P&L, Burn & Runway'!I17/'Kedge P&L, Burn & Runway'!I15,0),"") -> 10.138494 | ... Y19: =IF(IF(IF(ISERROR('Kedge P&L, Burn & Runway'!Y15>0),'Kedge P&L, Burn & Runway'!Y15>0,IF('Kedge P&L, Burn & Runway'!Y15="","",'Kedge P&L, Burn & Runway'!Y15>0))="",FALSE,IF(ISERROR('Kedge P&L, Burn & Runway'!Y15>0),'Kedge P&L, Burn & Runway'!Y15>0,IF('Kedge P&L, Burn & Runway'!Y15="","",'Kedge P&L, Burn & Runway'!Y15>0))),IF(IF(IF(ISERROR('Kedge P&L, Burn & Runway'!Y17>0),'Kedge P&L, Burn & Runway'!Y17>0,IF('Kedge P&L, Burn & Runway'!Y17="","",'Kedge P&L, Burn & Runway'!Y17>0))="",FALSE,IF(ISERROR('Kedge P&L, Burn & Runway'!Y17>0),'Kedge P&L, Burn & Runway'!Y17>0,IF('Kedge P&L, Burn & Runway'!Y17="","",'Kedge P&L, Burn & Runway'!Y17>0))),'Kedge P&L, Burn & Runway'!Y17/'Kedge P&L, Burn & Runway'!Y15,0),"") -> 0

Sheet Stress Unit Economics & Funding
A1: Stress Unit Economics & Funding
A2: Operating Model · Stress: Sonnet on big repos
A4: Variable / dimension | B4: 2026-10 | C4: 2026-11 | D4: 2026-12 | E4: 2027-01 | F4: 2027-02 | G4: 2027-03 | H4: 2027-04 | I4: 2027-05 | J4: 2027-06 | K4: 2027-07 | L4: 2027-08 | M4: 2027-09 | N4: 2027-10 | O4: 2027-11 | P4: 2027-12 | Q4: 2028-01 | R4: 2028-02 | S4: 2028-03 | T4: 2028-04 | U4: 2028-05 | V4: 2028-06 | W4: 2028-07 | X4: 2028-08 | Y4: 2028-09
A5: Contribution per active team | B5: ='Model inputs'!AA26*'Model inputs'!AA15*('Model inputs'!AA25*(1-'Model inputs'!AA24)-'Model inputs'!AA18) -> 82.2 | C5: ='Model inputs'!AA26*'Model inputs'!AA15*('Model inputs'!AA25*(1-'Model inputs'!AA24)-'Model inputs'!AA18) -> 82.2 | D5: ='Model inputs'!AA26*'Model inputs'!AA15*('Model inputs'!AA25*(1-'Model inputs'!AA24)-'Model inputs'!AA18) -> 82.2 | E5: ='Model inputs'!AA26*'Model inputs'!AA15*('Model inputs'!AA25*(1-'Model inputs'!AA24)-'Model inputs'!AA18) -> 82.2 | F5: ='Model inputs'!AA26*'Model inputs'!AA15*('Model inputs'!AA25*(1-'Model inputs'!AA24)-'Model inputs'!AA18) -> 82.2 | G5: ='Model inputs'!AA26*'Model inputs'!AA15*('Model inputs'!AA25*(1-'Model inputs'!AA24)-'Model inputs'!AA18) -> 82.2 | H5: ='Model inputs'!AA26*'Model inputs'!AA15*('Model inputs'!AA25*(1-'Model inputs'!AA24)-'Model inputs'!AA18) -> 82.2 | I5: ='Model inputs'!AA26*'Model inputs'!AA15*('Model inputs'!AA25*(1-'Model inputs'!AA24)-'Model inputs'!AA18) -> 82.2 | J5: ='Model inputs'!AA26*'Model inputs'!AA15*('Model inputs'!AA25*(1-'Model inputs'!AA24)-'Model inputs'!AA18) -> 82.2 | K5: ='Model inputs'!AA26*'Model inputs'!AA15*('Model inputs'!AA25*(1-'Model inputs'!AA24)-'Model inputs'!AA18) -> 82.2 | L5: ='Model inputs'!AA26*'Model inputs'!AA15*('Model inputs'!AA25*(1-'Model inputs'!AA24)-'Model inputs'!AA18) -> 82.2 | M5: ='Model inputs'!AA26*'Model inputs'!AA15*('Model inputs'!AA25*(1-'Model inputs'!AA24)-'Model inputs'!AA18) -> 82.2 | N5: ='Model inputs'!AA26*'Model inputs'!AA15*('Model inputs'!AA25*(1-'Model inputs'!AA24)-'Model inputs'!AA18) -> 82.2 | O5: ='Model inputs'!AA26*'Model inputs'!AA15*('Model inputs'!AA25*(1-'Model inputs'!AA24)-'Model inputs'!AA18) -> 82.2 | P5: ='Model inputs'!AA26*'Model inputs'!AA15*('Model inputs'!AA25*(1-'Model inputs'!AA24)-'Model inputs'!AA18) -> 82.2 | Q5: ='Model inputs'!AA26*'Model inputs'!AA15*('Model inputs'!AA25*(1-'Model inputs'!AA24)-'Model inputs'!AA18) -> 82.2 | R5: ='Model inputs'!AA26*'Model inputs'!AA15*('Model inputs'!AA25*(1-'Model inputs'!AA24)-'Model inputs'!AA18) -> 82.2 | S5: ='Model inputs'!AA26*'Model inputs'!AA15*('Model inputs'!AA25*(1-'Model inputs'!AA24)-'Model inputs'!AA18) -> 82.2 | T5: ='Model inputs'!AA26*'Model inputs'!AA15*('Model inputs'!AA25*(1-'Model inputs'!AA24)-'Model inputs'!AA18) -> 82.2 | U5: ='Model inputs'!AA26*'Model inputs'!AA15*('Model inputs'!AA25*(1-'Model inputs'!AA24)-'Model inputs'!AA18) -> 82.2 | V5: ='Model inputs'!AA26*'Model inputs'!AA15*('Model inputs'!AA25*(1-'Model inputs'!AA24)-'Model inputs'!AA18) -> 82.2 | W5: ='Model inputs'!AA26*'Model inputs'!AA15*('Model inputs'!AA25*(1-'Model inputs'!AA24)-'Model inputs'!AA18) -> 82.2 | X5: ='Model inputs'!AA26*'Model inputs'!AA15*('Model inputs'!AA25*(1-'Model inputs'!AA24)-'Model inputs'!AA18) -> 82.2 | Y5: ='Model inputs'!AA26*'Model inputs'!AA15*('Model inputs'!AA25*(1-'Model inputs'!AA24)-'Model inputs'!AA18) -> 82.2
A6: Active teams for paid-founder break-even | B6: =CEILING(('Model inputs'!AA13*'Model inputs'!AA11+'Model inputs'!AA29)/'Stress Unit Economics & Funding'!B5,1) -> 100 | C6: =CEILING(('Model inputs'!AA13*'Model inputs'!AA11+'Model inputs'!AA29)/'Stress Unit Economics & Funding'!C5,1) -> 100 | D6: =CEILING(('Model inputs'!AA13*'Model inputs'!AA11+'Model inputs'!AA29)/'Stress Unit Economics & Funding'!D5,1) -> 100 | E6: =CEILING(('Model inputs'!AA13*'Model inputs'!AA11+'Model inputs'!AA29)/'Stress Unit Economics & Funding'!E5,1) -> 100 | F6: =CEILING(('Model inputs'!AA13*'Model inputs'!AA11+'Model inputs'!AA29)/'Stress Unit Economics & Funding'!F5,1) -> 100 | G6: =CEILING(('Model inputs'!AA13*'Model inputs'!AA11+'Model inputs'!AA29)/'Stress Unit Economics & Funding'!G5,1) -> 100 | H6: =CEILING(('Model inputs'!AA13*'Model inputs'!AA11+'Model inputs'!AA29)/'Stress Unit Economics & Funding'!H5,1) -> 100 | I6: =CEILING(('Model inputs'!AA13*'Model inputs'!AA11+'Model inputs'!AA29)/'Stress Unit Economics & Funding'!I5,1) -> 100 | J6: =CEILING(('Model inputs'!AA13*'Model inputs'!AA11+'Model inputs'!AA29)/'Stress Unit Economics & Funding'!J5,1) -> 100 | K6: =CEILING(('Model inputs'!AA13*'Model inputs'!AA11+'Model inputs'!AA29)/'Stress Unit Economics & Funding'!K5,1) -> 100 | L6: =CEILING(('Model inputs'!AA13*'Model inputs'!AA11+'Model inputs'!AA29)/'Stress Unit Economics & Funding'!L5,1) -> 100 | M6: =CEILING(('Model inputs'!AA13*'Model inputs'!AA11+'Model inputs'!AA29)/'Stress Unit Economics & Funding'!M5,1) -> 100 | N6: =CEILING(('Model inputs'!AA13*'Model inputs'!AA11+'Model inputs'!AA29)/'Stress Unit Economics & Funding'!N5,1) -> 100 | O6: =CEILING(('Model inputs'!AA13*'Model inputs'!AA11+'Model inputs'!AA29)/'Stress Unit Economics & Funding'!O5,1) -> 100 | P6: =CEILING(('Model inputs'!AA13*'Model inputs'!AA11+'Model inputs'!AA29)/'Stress Unit Economics & Funding'!P5,1) -> 100 | Q6: =CEILING(('Model inputs'!AA13*'Model inputs'!AA11+'Model inputs'!AA29)/'Stress Unit Economics & Funding'!Q5,1) -> 100 | R6: =CEILING(('Model inputs'!AA13*'Model inputs'!AA11+'Model inputs'!AA29)/'Stress Unit Economics & Funding'!R5,1) -> 100 | S6: =CEILING(('Model inputs'!AA13*'Model inputs'!AA11+'Model inputs'!AA29)/'Stress Unit Economics & Funding'!S5,1) -> 100 | T6: =CEILING(('Model inputs'!AA13*'Model inputs'!AA11+'Model inputs'!AA29)/'Stress Unit Economics & Funding'!T5,1) -> 100 | U6: =CEILING(('Model inputs'!AA13*'Model inputs'!AA11+'Model inputs'!AA29)/'Stress Unit Economics & Funding'!U5,1) -> 100 | V6: =CEILING(('Model inputs'!AA13*'Model inputs'!AA11+'Model inputs'!AA29)/'Stress Unit Economics & Funding'!V5,1) -> 100 | W6: =CEILING(('Model inputs'!AA13*'Model inputs'!AA11+'Model inputs'!AA29)/'Stress Unit Economics & Funding'!W5,1) -> 100 | X6: =CEILING(('Model inputs'!AA13*'Model inputs'!AA11+'Model inputs'!AA29)/'Stress Unit Economics & Funding'!X5,1) -> 100 | Y6: =CEILING(('Model inputs'!AA13*'Model inputs'!AA11+'Model inputs'!AA29)/'Stress Unit Economics & Funding'!Y5,1) -> 100
A7: Cash excluding raises | B7: ='Model inputs'!B8-'Kedge P&L, Burn & Runway'!B15 -> 211 | C7: ='Stress Unit Economics & Funding'!B7-'Kedge P&L, Burn & Runway'!C15 -> 758.27273 | D7: ='Stress Unit Economics & Funding'!C7-'Kedge P&L, Burn & Runway'!D15 -> 1641.8182 | E7: ='Stress Unit Economics & Funding'!D7-'Kedge P&L, Burn & Runway'!E15 -> 2861.6364 | F7: ='Stress Unit Economics & Funding'!E7-'Kedge P&L, Burn & Runway'!F15 -> 4417.7273 | G7: ='Stress Unit Economics & Funding'!F7-'Kedge P&L, Burn & Runway'!G15 -> 6310.0909 | H7: ='Stress Unit Economics & Funding'!G7-'Kedge P&L, Burn & Runway'!H15 -> 538.72727 | I7: ='Stress Unit Economics & Funding'!H7-'Kedge P&L, Burn & Runway'!I15 -> -4896.3636 | J7: ='Stress Unit Economics & Funding'!I7-'Kedge P&L, Burn & Runway'!J15 -> -9995.1818 | ... Y7: ='Stress Unit Economics & Funding'!X7-'Kedge P&L, Burn & Runway'!Y15 -> -72354
A8: Total minimum funding needed | B8: =MAX(0,-'Stress Unit Economics & Funding'!B7,'Model inputs'!B30) -> 0 | C8: =MAX(0,-'Stress Unit Economics & Funding'!C7,'Stress Unit Economics & Funding'!B8) -> 0 | D8: =MAX(0,-'Stress Unit Economics & Funding'!D7,'Stress Unit Economics & Funding'!C8) -> 0 | E8: =MAX(0,-'Stress Unit Economics & Funding'!E7,'Stress Unit Economics & Funding'!D8) -> 0 | F8: =MAX(0,-'Stress Unit Economics & Funding'!F7,'Stress Unit Economics & Funding'!E8) -> 0 | G8: =MAX(0,-'Stress Unit Economics & Funding'!G7,'Stress Unit Economics & Funding'!F8) -> 0 | H8: =MAX(0,-'Stress Unit Economics & Funding'!H7,'Stress Unit Economics & Funding'!G8) -> 0 | I8: =MAX(0,-'Stress Unit Economics & Funding'!I7,'Stress Unit Economics & Funding'!H8) -> 4896.3636 | J8: =MAX(0,-'Stress Unit Economics & Funding'!J7,'Stress Unit Economics & Funding'!I8) -> 9995.1818 | ... Y8: =MAX(0,-'Stress Unit Economics & Funding'!Y7,'Stress Unit Economics & Funding'!X8) -> 72354

Sheet Model inputs
A1: Model inputs
A2: Integration values are aggregated snapshots; raw source records are not included.
A4: Variables
A5: Variable / segment | B5: 2026-09 | C5: 2026-10 | D5: 2026-11 | E5: 2026-12 | F5: 2027-01 | G5: 2027-02 | H5: 2027-03 | I5: 2027-04 | J5: 2027-05 | K5: 2027-06 | L5: 2027-07 | M5: 2027-08 | N5: 2027-09 | O5: 2027-10 | P5: 2027-11 | Q5: 2027-12 | R5: 2028-01 | S5: 2028-02 | T5: 2028-03 | U5: 2028-04 | V5: 2028-05 | W5: 2028-06 | X5: 2028-07 | Y5: 2028-08 | Z5: 2028-09 | AA5: Value | AB5: 2026-01 | AC5: 2026-02 | AD5: 2026-03 | AE5: 2026-04 | AF5: 2026-05 | AG5: 2026-06 | AH5: 2026-07 | AI5: 2026-08
A6: AI model costs | B6: 0 | C6: ='Model inputs'!C16*'Model inputs'!AA18 -> 171 | D6: ='Model inputs'!D16*'Model inputs'!AA18 -> 310.90909 | E6: ='Model inputs'!E16*'Model inputs'!AA18 -> 450.81818 | F6: ='Model inputs'!F16*'Model inputs'!AA18 -> 590.72727 | G6: ='Model inputs'!G16*'Model inputs'!AA18 -> 730.63636 | H6: ='Model inputs'!H16*'Model inputs'!AA18 -> 870.54545 | I6: ='Model inputs'!I16*'Model inputs'!AA18 -> 1010.4545 | J6: ='Model inputs'!J16*'Model inputs'!AA18 -> 1150.3636 | K6: ='Model inputs'!K16*'Model inputs'!AA18 -> 1290.2727 | L6: ='Model inputs'!L16*'Model inputs'!AA18 -> 1430.1818 | M6: ='Model inputs'!M16*'Model inputs'!AA18 -> 1570.0909 | N6: ='Model inputs'!N16*'Model inputs'!AA18 -> 1710 | O6: ='Model inputs'!O16*'Model inputs'!AA18 -> 1710 | P6: ='Model inputs'!P16*'Model inputs'!AA18 -> 1710 | Q6: ='Model inputs'!Q16*'Model inputs'!AA18 -> 1710 | R6: ='Model inputs'!R16*'Model inputs'!AA18 -> 1710 | S6: ='Model inputs'!S16*'Model inputs'!AA18 -> 1710 | T6: ='Model inputs'!T16*'Model inputs'!AA18 -> 1710 | U6: ='Model inputs'!U16*'Model inputs'!AA18 -> 1710 | V6: ='Model inputs'!V16*'Model inputs'!AA18 -> 1710 | W6: ='Model inputs'!W16*'Model inputs'!AA18 -> 1710 | X6: ='Model inputs'!X16*'Model inputs'!AA18 -> 1710 | Y6: ='Model inputs'!Y16*'Model inputs'!AA18 -> 1710 | Z6: ='Model inputs'!Z16*'Model inputs'!AA18 -> 1710
A7: Cash balance | B7: =IF('Model inputs'!AA34="","",'Model inputs'!AA34) -> 0 | C7: ='Model inputs'!B7-'Model inputs'!C20+'Model inputs'!C10 -> 211 | D7: ='Model inputs'!C7-'Model inputs'!D20+'Model inputs'!D10 -> 758.27273 | E7: ='Model inputs'!D7-'Model inputs'!E20+'Model inputs'!E10 -> 1641.8182 | F7: ='Model inputs'!E7-'Model inputs'!F20+'Model inputs'!F10 -> 2861.6364 | G7: ='Model inputs'!F7-'Model inputs'!G20+'Model inputs'!G10 -> 4417.7273 | H7: ='Model inputs'!G7-'Model inputs'!H20+'Model inputs'!H10 -> 6310.0909 | I7: ='Model inputs'!H7-'Model inputs'!I20+'Model inputs'!I10 -> 60538.727 | J7: ='Model inputs'!I7-'Model inputs'!J20+'Model inputs'!J10 -> 55103.636 | ... Z7: ='Model inputs'!Y7-'Model inputs'!Z20+'Model inputs'!Z10 -> -12354
A8: Cash excluding raises | B8: =IF('Model inputs'!AA34="","",'Model inputs'!AA34) -> 0 | C8: ='Model inputs'!B8-'Model inputs'!C20 -> 211 | D8: ='Model inputs'!C8-'Model inputs'!D20 -> 758.27273 | E8: ='Model inputs'!D8-'Model inputs'!E20 -> 1641.8182 | F8: ='Model inputs'!E8-'Model inputs'!F20 -> 2861.6364 | G8: ='Model inputs'!F8-'Model inputs'!G20 -> 4417.7273 | H8: ='Model inputs'!G8-'Model inputs'!H20 -> 6310.0909 | I8: ='Model inputs'!H8-'Model inputs'!I20 -> 538.72727 | J8: ='Model inputs'!I8-'Model inputs'!J20 -> -4896.3636 | ... Z8: ='Model inputs'!Y8-'Model inputs'!Z20 -> -72354
A9: Cost of goods sold | B9: 0 | C9: ='Model inputs'!C6+'Model inputs'!C23 -> 189 | D9: ='Model inputs'!D6+'Model inputs'!D23 -> 343.63636 | E9: ='Model inputs'!E6+'Model inputs'!E23 -> 498.27273 | F9: ='Model inputs'!F6+'Model inputs'!F23 -> 652.90909 | G9: ='Model inputs'!G6+'Model inputs'!G23 -> 807.54545 | H9: ='Model inputs'!H6+'Model inputs'!H23 -> 962.18182 | I9: ='Model inputs'!I6+'Model inputs'!I23 -> 1116.8182 | J9: ='Model inputs'!J6+'Model inputs'!J23 -> 1271.4545 | ... Z9: ='Model inputs'!Z6+'Model inputs'!Z23 -> 1890
A10: Equity raised | B10: 0 | C10: 0 | D10: 0 | E10: 0 | F10: 0 | G10: 0 | H10: 0 | I10: =60000 -> 60000 | J10: 0 | K10: 0 | L10: 0 | M10: 0 | N10: 0 | O10: 0 | P10: 0 | Q10: 0 | R10: 0 | S10: 0 | T10: 0 | U10: 0 | V10: 0 | W10: 0 | X10: 0 | Y10: 0 | Z10: 0
A11: Founder monthly salary | AA11: =4000 -> 4000
A12: Founder salaries | B12: 0 | C12: =IF(IF(IF(ISERROR('Model inputs'!C19>'Model inputs'!AA31),'Model inputs'!C19>'Model inputs'!AA31,IF(OR('Model inputs'!C19="",'Model inputs'!AA31=""),"",'Model inputs'!C19>'Model inputs'!AA31))="",FALSE,IF(ISERROR('Model inputs'!C19>'Model inputs'!AA31),'Model inputs'!C19>'Model inputs'!AA31,IF(OR('Model inputs'!C19="",'Model inputs'!AA31=""),"",'Model inputs'!C19>'Model inputs'!AA31))),'Model inputs'!AA13*'Model inputs'!AA11,0) -> 0 | D12: =IF(IF(IF(ISERROR('Model inputs'!D19>'Model inputs'!AA31),'Model inputs'!D19>'Model inputs'!AA31,IF(OR('Model inputs'!D19="",'Model inputs'!AA31=""),"",'Model inputs'!D19>'Model inputs'!AA31))="",FALSE,IF(ISERROR('Model inputs'!D19>'Model inputs'!AA31),'Model inputs'!D19>'Model inputs'!AA31,IF(OR('Model inputs'!D19="",'Model inputs'!AA31=""),"",'Model inputs'!D19>'Model inputs'!AA31))),'Model inputs'!AA13*'Model inputs'!AA11,0) -> 0 | E12: =IF(IF(IF(ISERROR('Model inputs'!E19>'Model inputs'!AA31),'Model inputs'!E19>'Model inputs'!AA31,IF(OR('Model inputs'!E19="",'Model inputs'!AA31=""),"",'Model inputs'!E19>'Model inputs'!AA31))="",FALSE,IF(ISERROR('Model inputs'!E19>'Model inputs'!AA31),'Model inputs'!E19>'Model inputs'!AA31,IF(OR('Model inputs'!E19="",'Model inputs'!AA31=""),"",'Model inputs'!E19>'Model inputs'!AA31))),'Model inputs'!AA13*'Model inputs'!AA11,0) -> 0 | F12: =IF(IF(IF(ISERROR('Model inputs'!F19>'Model inputs'!AA31),'Model inputs'!F19>'Model inputs'!AA31,IF(OR('Model inputs'!F19="",'Model inputs'!AA31=""),"",'Model inputs'!F19>'Model inputs'!AA31))="",FALSE,IF(ISERROR('Model inputs'!F19>'Model inputs'!AA31),'Model inputs'!F19>'Model inputs'!AA31,IF(OR('Model inputs'!F19="",'Model inputs'!AA31=""),"",'Model inputs'!F19>'Model inputs'!AA31))),'Model inputs'!AA13*'Model inputs'!AA11,0) -> 0 | G12: =IF(IF(IF(ISERROR('Model inputs'!G19>'Model inputs'!AA31),'Model inputs'!G19>'Model inputs'!AA31,IF(OR('Model inputs'!G19="",'Model inputs'!AA31=""),"",'Model inputs'!G19>'Model inputs'!AA31))="",FALSE,IF(ISERROR('Model inputs'!G19>'Model inputs'!AA31),'Model inputs'!G19>'Model inputs'!AA31,IF(OR('Model inputs'!G19="",'Model inputs'!AA31=""),"",'Model inputs'!G19>'Model inputs'!AA31))),'Model inputs'!AA13*'Model inputs'!AA11,0) -> 0 | H12: =IF(IF(IF(ISERROR('Model inputs'!H19>'Model inputs'!AA31),'Model inputs'!H19>'Model inputs'!AA31,IF(OR('Model inputs'!H19="",'Model inputs'!AA31=""),"",'Model inputs'!H19>'Model inputs'!AA31))="",FALSE,IF(ISERROR('Model inputs'!H19>'Model inputs'!AA31),'Model inputs'!H19>'Model inputs'!AA31,IF(OR('Model inputs'!H19="",'Model inputs'!AA31=""),"",'Model inputs'!H19>'Model inputs'!AA31))),'Model inputs'!AA13*'Model inputs'!AA11,0) -> 0 | I12: =IF(IF(IF(ISERROR('Model inputs'!I19>'Model inputs'!AA31),'Model inputs'!I19>'Model inputs'!AA31,IF(OR('Model inputs'!I19="",'Model inputs'!AA31=""),"",'Model inputs'!I19>'Model inputs'!AA31))="",FALSE,IF(ISERROR('Model inputs'!I19>'Model inputs'!AA31),'Model inputs'!I19>'Model inputs'!AA31,IF(OR('Model inputs'!I19="",'Model inputs'!AA31=""),"",'Model inputs'!I19>'Model inputs'!AA31))),'Model inputs'!AA13*'Model inputs'!AA11,0) -> 8000 | J12: =IF(IF(IF(ISERROR('Model inputs'!J19>'Model inputs'!AA31),'Model inputs'!J19>'Model inputs'!AA31,IF(OR('Model inputs'!J19="",'Model inputs'!AA31=""),"",'Model inputs'!J19>'Model inputs'!AA31))="",FALSE,IF(ISERROR('Model inputs'!J19>'Model inputs'!AA31),'Model inputs'!J19>'Model inputs'!AA31,IF(OR('Model inputs'!J19="",'Model inputs'!AA31=""),"",'Model inputs'!J19>'Model inputs'!AA31))),'Model inputs'!AA13*'Model inputs'!AA11,0) -> 8000 | K12: =IF(IF(IF(ISERROR('Model inputs'!K19>'Model inputs'!AA31),'Model inputs'!K19>'Model inputs'!AA31,IF(OR('Model inputs'!K19="",'Model inputs'!AA31=""),"",'Model inputs'!K19>'Model inputs'!AA31))="",FALSE,IF(ISERROR('Model inputs'!K19>'Model inputs'!AA31),'Model inputs'!K19>'Model inputs'!AA31,IF(OR('Model inputs'!K19="",'Model inputs'!AA31=""),"",'Model inputs'!K19>'Model inputs'!AA31))),'Model inputs'!AA13*'Model inputs'!AA11,0) -> 8000 | L12: =IF(IF(IF(ISERROR('Model inputs'!L19>'Model inputs'!AA31),'Model inputs'!L19>'Model inputs'!AA31,IF(OR('Model inputs'!L19="",'Model inputs'!AA31=""),"",'Model inputs'!L19>'Model inputs'!AA31))="",FALSE,IF(ISERROR('Model inputs'!L19>'Model inputs'!AA31),'Model inputs'!L19>'Model inputs'!AA31,IF(OR('Model inputs'!L19="",'Model inputs'!AA31=""),"",'Model inputs'!L19>'Model inputs'!AA31))),'Model inputs'!AA13*'Model inputs'!AA11,0) -> 8000 | M12: =IF(IF(IF(ISERROR('Model inputs'!M19>'Model inputs'!AA31),'Model inputs'!M19>'Model inputs'!AA31,IF(OR('Model inputs'!M19="",'Model inputs'!AA31=""),"",'Model inputs'!M19>'Model inputs'!AA31))="",FALSE,IF(ISERROR('Model inputs'!M19>'Model inputs'!AA31),'Model inputs'!M19>'Model inputs'!AA31,IF(OR('Model inputs'!M19="",'Model inputs'!AA31=""),"",'Model inputs'!M19>'Model inputs'!AA31))),'Model inputs'!AA13*'Model inputs'!AA11,0) -> 8000 | N12: =IF(IF(IF(ISERROR('Model inputs'!N19>'Model inputs'!AA31),'Model inputs'!N19>'Model inputs'!AA31,IF(OR('Model inputs'!N19="",'Model inputs'!AA31=""),"",'Model inputs'!N19>'Model inputs'!AA31))="",FALSE,IF(ISERROR('Model inputs'!N19>'Model inputs'!AA31),'Model inputs'!N19>'Model inputs'!AA31,IF(OR('Model inputs'!N19="",'Model inputs'!AA31=""),"",'Model inputs'!N19>'Model inputs'!AA31))),'Model inputs'!AA13*'Model inputs'!AA11,0) -> 8000 | O12: =IF(IF(IF(ISERROR('Model inputs'!O19>'Model inputs'!AA31),'Model inputs'!O19>'Model inputs'!AA31,IF(OR('Model inputs'!O19="",'Model inputs'!AA31=""),"",'Model inputs'!O19>'Model inputs'!AA31))="",FALSE,IF(ISERROR('Model inputs'!O19>'Model inputs'!AA31),'Model inputs'!O19>'Model inputs'!AA31,IF(OR('Model inputs'!O19="",'Model inputs'!AA31=""),"",'Model inputs'!O19>'Model inputs'!AA31))),'Model inputs'!AA13*'Model inputs'!AA11,0) -> 8000 | P12: =IF(IF(IF(ISERROR('Model inputs'!P19>'Model inputs'!AA31),'Model inputs'!P19>'Model inputs'!AA31,IF(OR('Model inputs'!P19="",'Model inputs'!AA31=""),"",'Model inputs'!P19>'Model inputs'!AA31))="",FALSE,IF(ISERROR('Model inputs'!P19>'Model inputs'!AA31),'Model inputs'!P19>'Model inputs'!AA31,IF(OR('Model inputs'!P19="",'Model inputs'!AA31=""),"",'Model inputs'!P19>'Model inputs'!AA31))),'Model inputs'!AA13*'Model inputs'!AA11,0) -> 8000 | Q12: =IF(IF(IF(ISERROR('Model inputs'!Q19>'Model inputs'!AA31),'Model inputs'!Q19>'Model inputs'!AA31,IF(OR('Model inputs'!Q19="",'Model inputs'!AA31=""),"",'Model inputs'!Q19>'Model inputs'!AA31))="",FALSE,IF(ISERROR('Model inputs'!Q19>'Model inputs'!AA31),'Model inputs'!Q19>'Model inputs'!AA31,IF(OR('Model inputs'!Q19="",'Model inputs'!AA31=""),"",'Model inputs'!Q19>'Model inputs'!AA31))),'Model inputs'!AA13*'Model inputs'!AA11,0) -> 8000 | R12: =IF(IF(IF(ISERROR('Model inputs'!R19>'Model inputs'!AA31),'Model inputs'!R19>'Model inputs'!AA31,IF(OR('Model inputs'!R19="",'Model inputs'!AA31=""),"",'Model inputs'!R19>'Model inputs'!AA31))="",FALSE,IF(ISERROR('Model inputs'!R19>'Model inputs'!AA31),'Model inputs'!R19>'Model inputs'!AA31,IF(OR('Model inputs'!R19="",'Model inputs'!AA31=""),"",'Model inputs'!R19>'Model inputs'!AA31))),'Model inputs'!AA13*'Model inputs'!AA11,0) -> 8000 | S12: =IF(IF(IF(ISERROR('Model inputs'!S19>'Model inputs'!AA31),'Model inputs'!S19>'Model inputs'!AA31,IF(OR('Model inputs'!S19="",'Model inputs'!AA31=""),"",'Model inputs'!S19>'Model inputs'!AA31))="",FALSE,IF(ISERROR('Model inputs'!S19>'Model inputs'!AA31),'Model inputs'!S19>'Model inputs'!AA31,IF(OR('Model inputs'!S19="",'Model inputs'!AA31=""),"",'Model inputs'!S19>'Model inputs'!AA31))),'Model inputs'!AA13*'Model inputs'!AA11,0) -> 8000 | T12: =IF(IF(IF(ISERROR('Model inputs'!T19>'Model inputs'!AA31),'Model inputs'!T19>'Model inputs'!AA31,IF(OR('Model inputs'!T19="",'Model inputs'!AA31=""),"",'Model inputs'!T19>'Model inputs'!AA31))="",FALSE,IF(ISERROR('Model inputs'!T19>'Model inputs'!AA31),'Model inputs'!T19>'Model inputs'!AA31,IF(OR('Model inputs'!T19="",'Model inputs'!AA31=""),"",'Model inputs'!T19>'Model inputs'!AA31))),'Model inputs'!AA13*'Model inputs'!AA11,0) -> 8000 | U12: =IF(IF(IF(ISERROR('Model inputs'!U19>'Model inputs'!AA31),'Model inputs'!U19>'Model inputs'!AA31,IF(OR('Model inputs'!U19="",'Model inputs'!AA31=""),"",'Model inputs'!U19>'Model inputs'!AA31))="",FALSE,IF(ISERROR('Model inputs'!U19>'Model inputs'!AA31),'Model inputs'!U19>'Model inputs'!AA31,IF(OR('Model inputs'!U19="",'Model inputs'!AA31=""),"",'Model inputs'!U19>'Model inputs'!AA31))),'Model inputs'!AA13*'Model inputs'!AA11,0) -> 8000 | V12: =IF(IF(IF(ISERROR('Model inputs'!V19>'Model inputs'!AA31),'Model inputs'!V19>'Model inputs'!AA31,IF(OR('Model inputs'!V19="",'Model inputs'!AA31=""),"",'Model inputs'!V19>'Model inputs'!AA31))="",FALSE,IF(ISERROR('Model inputs'!V19>'Model inputs'!AA31),'Model inputs'!V19>'Model inputs'!AA31,IF(OR('Model inputs'!V19="",'Model inputs'!AA31=""),"",'Model inputs'!V19>'Model inputs'!AA31))),'Model inputs'!AA13*'Model inputs'!AA11,0) -> 8000 | W12: =IF(IF(IF(ISERROR('Model inputs'!W19>'Model inputs'!AA31),'Model inputs'!W19>'Model inputs'!AA31,IF(OR('Model inputs'!W19="",'Model inputs'!AA31=""),"",'Model inputs'!W19>'Model inputs'!AA31))="",FALSE,IF(ISERROR('Model inputs'!W19>'Model inputs'!AA31),'Model inputs'!W19>'Model inputs'!AA31,IF(OR('Model inputs'!W19="",'Model inputs'!AA31=""),"",'Model inputs'!W19>'Model inputs'!AA31))),'Model inputs'!AA13*'Model inputs'!AA11,0) -> 8000 | X12: =IF(IF(IF(ISERROR('Model inputs'!X19>'Model inputs'!AA31),'Model inputs'!X19>'Model inputs'!AA31,IF(OR('Model inputs'!X19="",'Model inputs'!AA31=""),"",'Model inputs'!X19>'Model inputs'!AA31))="",FALSE,IF(ISERROR('Model inputs'!X19>'Model inputs'!AA31),'Model inputs'!X19>'Model inputs'!AA31,IF(OR('Model inputs'!X19="",'Model inputs'!AA31=""),"",'Model inputs'!X19>'Model inputs'!AA31))),'Model inputs'!AA13*'Model inputs'!AA11,0) -> 8000 | Y12: =IF(IF(IF(ISERROR('Model inputs'!Y19>'Model inputs'!AA31),'Model inputs'!Y19>'Model inputs'!AA31,IF(OR('Model inputs'!Y19="",'Model inputs'!AA31=""),"",'Model inputs'!Y19>'Model inputs'!AA31))="",FALSE,IF(ISERROR('Model inputs'!Y19>'Model inputs'!AA31),'Model inputs'!Y19>'Model inputs'!AA31,IF(OR('Model inputs'!Y19="",'Model inputs'!AA31=""),"",'Model inputs'!Y19>'Model inputs'!AA31))),'Model inputs'!AA13*'Model inputs'!AA11,0) -> 8000 | Z12: =IF(IF(IF(ISERROR('Model inputs'!Z19>'Model inputs'!AA31),'Model inputs'!Z19>'Model inputs'!AA31,IF(OR('Model inputs'!Z19="",'Model inputs'!AA31=""),"",'Model inputs'!Z19>'Model inputs'!AA31))="",FALSE,IF(ISERROR('Model inputs'!Z19>'Model inputs'!AA31),'Model inputs'!Z19>'Model inputs'!AA31,IF(OR('Model inputs'!Z19="",'Model inputs'!AA31=""),"",'Model inputs'!Z19>'Model inputs'!AA31))),'Model inputs'!AA13*'Model inputs'!AA11,0) -> 8000
A13: Founders | AA13: =2 -> 2
A14: Funding needed to date | B14: =0 -> 0 | C14: =IF(IF(IF(ISERROR(-'Model inputs'!C7>'Model inputs'!B14),-'Model inputs'!C7>'Model inputs'!B14,IF('Model inputs'!B14="","",-'Model inputs'!C7>'Model inputs'!B14))="",FALSE,IF(ISERROR(-'Model inputs'!C7>'Model inputs'!B14),-'Model inputs'!C7>'Model inputs'!B14,IF('Model inputs'!B14="","",-'Model inputs'!C7>'Model inputs'!B14))),-'Model inputs'!C7,IF('Model inputs'!B14="","",'Model inputs'!B14)) -> 0 | D14: =IF(IF(IF(ISERROR(-'Model inputs'!D7>'Model inputs'!C14),-'Model inputs'!D7>'Model inputs'!C14,IF('Model inputs'!C14="","",-'Model inputs'!D7>'Model inputs'!C14))="",FALSE,IF(ISERROR(-'Model inputs'!D7>'Model inputs'!C14),-'Model inputs'!D7>'Model inputs'!C14,IF('Model inputs'!C14="","",-'Model inputs'!D7>'Model inputs'!C14))),-'Model inputs'!D7,IF('Model inputs'!C14="","",'Model inputs'!C14)) -> 0 | E14: =IF(IF(IF(ISERROR(-'Model inputs'!E7>'Model inputs'!D14),-'Model inputs'!E7>'Model inputs'!D14,IF('Model inputs'!D14="","",-'Model inputs'!E7>'Model inputs'!D14))="",FALSE,IF(ISERROR(-'Model inputs'!E7>'Model inputs'!D14),-'Model inputs'!E7>'Model inputs'!D14,IF('Model inputs'!D14="","",-'Model inputs'!E7>'Model inputs'!D14))),-'Model inputs'!E7,IF('Model inputs'!D14="","",'Model inputs'!D14)) -> 0 | F14: =IF(IF(IF(ISERROR(-'Model inputs'!F7>'Model inputs'!E14),-'Model inputs'!F7>'Model inputs'!E14,IF('Model inputs'!E14="","",-'Model inputs'!F7>'Model inputs'!E14))="",FALSE,IF(ISERROR(-'Model inputs'!F7>'Model inputs'!E14),-'Model inputs'!F7>'Model inputs'!E14,IF('Model inputs'!E14="","",-'Model inputs'!F7>'Model inputs'!E14))),-'Model inputs'!F7,IF('Model inputs'!E14="","",'Model inputs'!E14)) -> 0 | G14: =IF(IF(IF(ISERROR(-'Model inputs'!G7>'Model inputs'!F14),-'Model inputs'!G7>'Model inputs'!F14,IF('Model inputs'!F14="","",-'Model inputs'!G7>'Model inputs'!F14))="",FALSE,IF(ISERROR(-'Model inputs'!G7>'Model inputs'!F14),-'Model inputs'!G7>'Model inputs'!F14,IF('Model inputs'!F14="","",-'Model inputs'!G7>'Model inputs'!F14))),-'Model inputs'!G7,IF('Model inputs'!F14="","",'Model inputs'!F14)) -> 0 | H14: =IF(IF(IF(ISERROR(-'Model inputs'!H7>'Model inputs'!G14),-'Model inputs'!H7>'Model inputs'!G14,IF('Model inputs'!G14="","",-'Model inputs'!H7>'Model inputs'!G14))="",FALSE,IF(ISERROR(-'Model inputs'!H7>'Model inputs'!G14),-'Model inputs'!H7>'Model inputs'!G14,IF('Model inputs'!G14="","",-'Model inputs'!H7>'Model inputs'!G14))),-'Model inputs'!H7,IF('Model inputs'!G14="","",'Model inputs'!G14)) -> 0 | I14: =IF(IF(IF(ISERROR(-'Model inputs'!I7>'Model inputs'!H14),-'Model inputs'!I7>'Model inputs'!H14,IF('Model inputs'!H14="","",-'Model inputs'!I7>'Model inputs'!H14))="",FALSE,IF(ISERROR(-'Model inputs'!I7>'Model inputs'!H14),-'Model inputs'!I7>'Model inputs'!H14,IF('Model inputs'!H14="","",-'Model inputs'!I7>'Model inputs'!H14))),-'Model inputs'!I7,IF('Model inputs'!H14="","",'Model inputs'!H14)) -> 0 | J14: =IF(IF(IF(ISERROR(-'Model inputs'!J7>'Model inputs'!I14),-'Model inputs'!J7>'Model inputs'!I14,IF('Model inputs'!I14="","",-'Model inputs'!J7>'Model inputs'!I14))="",FALSE,IF(ISERROR(-'Model inputs'!J7>'Model inputs'!I14),-'Model inputs'!J7>'Model inputs'!I14,IF('Model inputs'!I14="","",-'Model inputs'!J7>'Model inputs'!I14))),-'Model inputs'!J7,IF('Model inputs'!I14="","",'Model inputs'!I14)) -> 0 | ... Z14: =IF(IF(IF(ISERROR(-'Model inputs'!Z7>'Model inputs'!Y14),-'Model inputs'!Z7>'Model inputs'!Y14,IF('Model inputs'!Y14="","",-'Model inputs'!Z7>'Model inputs'!Y14))="",FALSE,IF(ISERROR(-'Model inputs'!Z7>'Model inputs'!Y14),-'Model inputs'!Z7>'Model inputs'!Y14,IF('Model inputs'!Y14="","",-'Model inputs'!Z7>'Model inputs'!Y14))),-'Model inputs'!Z7,IF('Model inputs'!Y14="","",'Model inputs'!Y14)) -> 12354
A15: Green PR rate | AA15: =0.6 -> 0.6
A16: Green PRs | B16: 0 | C16: ='Model inputs'!C32*'Model inputs'!AA15 -> 60 | D16: ='Model inputs'!D32*'Model inputs'!AA15 -> 109.09091 | E16: ='Model inputs'!E32*'Model inputs'!AA15 -> 158.18182 | F16: ='Model inputs'!F32*'Model inputs'!AA15 -> 207.27273 | G16: ='Model inputs'!G32*'Model inputs'!AA15 -> 256.36364 | H16: ='Model inputs'!H32*'Model inputs'!AA15 -> 305.45455 | I16: ='Model inputs'!I32*'Model inputs'!AA15 -> 354.54545 | J16: ='Model inputs'!J32*'Model inputs'!AA15 -> 403.63636 | K16: ='Model inputs'!K32*'Model inputs'!AA15 -> 452.72727 | L16: ='Model inputs'!L32*'Model inputs'!AA15 -> 501.81818 | M16: ='Model inputs'!M32*'Model inputs'!AA15 -> 550.90909 | N16: ='Model inputs'!N32*'Model inputs'!AA15 -> 600 | O16: ='Model inputs'!O32*'Model inputs'!AA15 -> 600 | P16: ='Model inputs'!P32*'Model inputs'!AA15 -> 600 | Q16: ='Model inputs'!Q32*'Model inputs'!AA15 -> 600 | R16: ='Model inputs'!R32*'Model inputs'!AA15 -> 600 | S16: ='Model inputs'!S32*'Model inputs'!AA15 -> 600 | T16: ='Model inputs'!T32*'Model inputs'!AA15 -> 600 | U16: ='Model inputs'!U32*'Model inputs'!AA15 -> 600 | V16: ='Model inputs'!V32*'Model inputs'!AA15 -> 600 | W16: ='Model inputs'!W32*'Model inputs'!AA15 -> 600 | X16: ='Model inputs'!X32*'Model inputs'!AA15 -> 600 | Y16: ='Model inputs'!Y32*'Model inputs'!AA15 -> 600 | Z16: ='Model inputs'!Z32*'Model inputs'!AA15 -> 600
A17: Gross profit | B17: 0 | C17: ='Model inputs'!C27-'Model inputs'!C9 -> 411 | D17: ='Model inputs'!D27-'Model inputs'!D9 -> 747.27273 | E17: ='Model inputs'!E27-'Model inputs'!E9 -> 1083.5455 | F17: ='Model inputs'!F27-'Model inputs'!F9 -> 1419.8182 | G17: ='Model inputs'!G27-'Model inputs'!G9 -> 1756.0909 | H17: ='Model inputs'!H27-'Model inputs'!H9 -> 2092.3636 | I17: ='Model inputs'!I27-'Model inputs'!I9 -> 2428.6364 | J17: ='Model inputs'!J27-'Model inputs'!J9 -> 2764.9091 | ... Z17: ='Model inputs'!Z27-'Model inputs'!Z9 -> 4110
A18: Model cost per green PR | AA18: =2.85 -> 2.85
A19: Month number | B19: =0 -> 0 | C19: ='Model inputs'!B19+1 -> 1 | D19: ='Model inputs'!C19+1 -> 2 | E19: ='Model inputs'!D19+1 -> 3 | F19: ='Model inputs'!E19+1 -> 4 | G19: ='Model inputs'!F19+1 -> 5 | H19: ='Model inputs'!G19+1 -> 6 | I19: ='Model inputs'!H19+1 -> 7 | J19: ='Model inputs'!I19+1 -> 8 | ... Z19: ='Model inputs'!Y19+1 -> 24
A20: Net burn | B20: 0 | C20: =-'Model inputs'!C22 -> -211 | D20: =-'Model inputs'!D22 -> -547.27273 | E20: =-'Model inputs'!E22 -> -883.54545 | F20: =-'Model inputs'!F22 -> -1219.8182 | G20: =-'Model inputs'!G22 -> -1556.0909 | H20: =-'Model inputs'!H22 -> -1892.3636 | I20: =-'Model inputs'!I22 -> 5771.3636 | J20: =-'Model inputs'!J22 -> 5435.0909 | ... Z20: =-'Model inputs'!Z22 -> 4090
A21: Operating expenses | B21: 0 | C21: ='Model inputs'!C12+'Model inputs'!C28 -> 200 | D21: ='Model inputs'!D12+'Model inputs'!D28 -> 200 | E21: ='Model inputs'!E12+'Model inputs'!E28 -> 200 | F21: ='Model inputs'!F12+'Model inputs'!F28 -> 200 | G21: ='Model inputs'!G12+'Model inputs'!G28 -> 200 | H21: ='Model inputs'!H12+'Model inputs'!H28 -> 200 | I21: ='Model inputs'!I12+'Model inputs'!I28 -> 8200 | J21: ='Model inputs'!J12+'Model inputs'!J28 -> 8200 | ... Z21: ='Model inputs'!Z12+'Model inputs'!Z28 -> 8200
A22: Operating income | B22: 0 | C22: ='Model inputs'!C17-'Model inputs'!C21 -> 211 | D22: ='Model inputs'!D17-'Model inputs'!D21 -> 547.27273 | E22: ='Model inputs'!E17-'Model inputs'!E21 -> 883.54545 | F22: ='Model inputs'!F17-'Model inputs'!F21 -> 1219.8182 | G22: ='Model inputs'!G17-'Model inputs'!G21 -> 1556.0909 | H22: ='Model inputs'!H17-'Model inputs'!H21 -> 1892.3636 | I22: ='Model inputs'!I17-'Model inputs'!I21 -> -5771.3636 | J22: ='Model inputs'!J17-'Model inputs'!J21 -> -5435.0909 | ... Z22: ='Model inputs'!Z17-'Model inputs'!Z21 -> -4090
A23: Payment processing | B23: 0 | C23: ='Model inputs'!C27*'Model inputs'!AA24 -> 18 | D23: ='Model inputs'!D27*'Model inputs'!AA24 -> 32.727273 | E23: ='Model inputs'!E27*'Model inputs'!AA24 -> 47.454545 | F23: ='Model inputs'!F27*'Model inputs'!AA24 -> 62.181818 | G23: ='Model inputs'!G27*'Model inputs'!AA24 -> 76.909091 | H23: ='Model inputs'!H27*'Model inputs'!AA24 -> 91.636364 | I23: ='Model inputs'!I27*'Model inputs'!AA24 -> 106.36364 | J23: ='Model inputs'!J27*'Model inputs'!AA24 -> 121.09091 | K23: ='Model inputs'!K27*'Model inputs'!AA24 -> 135.81818 | L23: ='Model inputs'!L27*'Model inputs'!AA24 -> 150.54545 | M23: ='Model inputs'!M27*'Model inputs'!AA24 -> 165.27273 | N23: ='Model inputs'!N27*'Model inputs'!AA24 -> 180 | O23: ='Model inputs'!O27*'Model inputs'!AA24 -> 180 | P23: ='Model inputs'!P27*'Model inputs'!AA24 -> 180 | Q23: ='Model inputs'!Q27*'Model inputs'!AA24 -> 180 | R23: ='Model inputs'!R27*'Model inputs'!AA24 -> 180 | S23: ='Model inputs'!S27*'Model inputs'!AA24 -> 180 | T23: ='Model inputs'!T27*'Model inputs'!AA24 -> 180 | U23: ='Model inputs'!U27*'Model inputs'!AA24 -> 180 | V23: ='Model inputs'!V27*'Model inputs'!AA24 -> 180 | W23: ='Model inputs'!W27*'Model inputs'!AA24 -> 180 | X23: ='Model inputs'!X27*'Model inputs'!AA24 -> 180 | Y23: ='Model inputs'!Y27*'Model inputs'!AA24 -> 180 | Z23: ='Model inputs'!Z27*'Model inputs'!AA24 -> 180
A24: Payment processing rate | AA24: =0.03 -> 0.03
A25: Price per green PR | AA25: =10 -> 10
A26: PRs submitted per team | AA26: =20 -> 20
A27: Revenue | B27: 0 | C27: ='Model inputs'!C16*'Model inputs'!AA25 -> 600 | D27: ='Model inputs'!D16*'Model inputs'!AA25 -> 1090.9091 | E27: ='Model inputs'!E16*'Model inputs'!AA25 -> 1581.8182 | F27: ='Model inputs'!F16*'Model inputs'!AA25 -> 2072.7273 | G27: ='Model inputs'!G16*'Model inputs'!AA25 -> 2563.6364 | H27: ='Model inputs'!H16*'Model inputs'!AA25 -> 3054.5455 | I27: ='Model inputs'!I16*'Model inputs'!AA25 -> 3545.4545 | J27: ='Model inputs'!J16*'Model inputs'!AA25 -> 4036.3636 | K27: ='Model inputs'!K16*'Model inputs'!AA25 -> 4527.2727 | L27: ='Model inputs'!L16*'Model inputs'!AA25 -> 5018.1818 | M27: ='Model inputs'!M16*'Model inputs'!AA25 -> 5509.0909 | N27: ='Model inputs'!N16*'Model inputs'!AA25 -> 6000 | O27: ='Model inputs'!O16*'Model inputs'!AA25 -> 6000 | P27: ='Model inputs'!P16*'Model inputs'!AA25 -> 6000 | Q27: ='Model inputs'!Q16*'Model inputs'!AA25 -> 6000 | R27: ='Model inputs'!R16*'Model inputs'!AA25 -> 6000 | S27: ='Model inputs'!S16*'Model inputs'!AA25 -> 6000 | T27: ='Model inputs'!T16*'Model inputs'!AA25 -> 6000 | U27: ='Model inputs'!U16*'Model inputs'!AA25 -> 6000 | V27: ='Model inputs'!V16*'Model inputs'!AA25 -> 6000 | W27: ='Model inputs'!W16*'Model inputs'!AA25 -> 6000 | X27: ='Model inputs'!X16*'Model inputs'!AA25 -> 6000 | Y27: ='Model inputs'!Y16*'Model inputs'!AA25 -> 6000 | Z27: ='Model inputs'!Z16*'Model inputs'!AA25 -> 6000
A28: Software and tools | B28: 0 | C28: =IF('Model inputs'!AA29="","",'Model inputs'!AA29) -> 200 | D28: =IF('Model inputs'!AA29="","",'Model inputs'!AA29) -> 200 | E28: =IF('Model inputs'!AA29="","",'Model inputs'!AA29) -> 200 | F28: =IF('Model inputs'!AA29="","",'Model inputs'!AA29) -> 200 | G28: =IF('Model inputs'!AA29="","",'Model inputs'!AA29) -> 200 | H28: =IF('Model inputs'!AA29="","",'Model inputs'!AA29) -> 200 | I28: =IF('Model inputs'!AA29="","",'Model inputs'!AA29) -> 200 | J28: =IF('Model inputs'!AA29="","",'Model inputs'!AA29) -> 200 | K28: =IF('Model inputs'!AA29="","",'Model inputs'!AA29) -> 200 | L28: =IF('Model inputs'!AA29="","",'Model inputs'!AA29) -> 200 | M28: =IF('Model inputs'!AA29="","",'Model inputs'!AA29) -> 200 | N28: =IF('Model inputs'!AA29="","",'Model inputs'!AA29) -> 200 | O28: =IF('Model inputs'!AA29="","",'Model inputs'!AA29) -> 200 | P28: =IF('Model inputs'!AA29="","",'Model inputs'!AA29) -> 200 | Q28: =IF('Model inputs'!AA29="","",'Model inputs'!AA29) -> 200 | R28: =IF('Model inputs'!AA29="","",'Model inputs'!AA29) -> 200 | S28: =IF('Model inputs'!AA29="","",'Model inputs'!AA29) -> 200 | T28: =IF('Model inputs'!AA29="","",'Model inputs'!AA29) -> 200 | U28: =IF('Model inputs'!AA29="","",'Model inputs'!AA29) -> 200 | V28: =IF('Model inputs'!AA29="","",'Model inputs'!AA29) -> 200 | W28: =IF('Model inputs'!AA29="","",'Model inputs'!AA29) -> 200 | X28: =IF('Model inputs'!AA29="","",'Model inputs'!AA29) -> 200 | Y28: =IF('Model inputs'!AA29="","",'Model inputs'!AA29) -> 200 | Z28: =IF('Model inputs'!AA29="","",'Model inputs'!AA29) -> 200
A29: Software and tools per month | AA29: =200 -> 200
A30: Total minimum funding needed | B30: =0 -> 0 | C30: =MAX(0,-'Model inputs'!C8,'Model inputs'!B30) -> 0 | D30: =MAX(0,-'Model inputs'!D8,'Model inputs'!C30) -> 0 | E30: =MAX(0,-'Model inputs'!E8,'Model inputs'!D30) -> 0 | F30: =MAX(0,-'Model inputs'!F8,'Model inputs'!E30) -> 0 | G30: =MAX(0,-'Model inputs'!G8,'Model inputs'!F30) -> 0 | H30: =MAX(0,-'Model inputs'!H8,'Model inputs'!G30) -> 0 | I30: =MAX(0,-'Model inputs'!I8,'Model inputs'!H30) -> 0 | J30: =MAX(0,-'Model inputs'!J8,'Model inputs'!I30) -> 4896.3636 | ... Z30: =MAX(0,-'Model inputs'!Z8,'Model inputs'!Y30) -> 72354
A31: Unpaid founder months · Kedge P&L, Burn & Runway | AA31: =6 -> 6
A32: Attempted PRs · Kedge P&L, Burn & Runway | B32: 0 | C32: ='Model inputs'!C35*'Model inputs'!AA26 -> 100 | D32: ='Model inputs'!D35*'Model inputs'!AA26 -> 181.81818 | E32: ='Model inputs'!E35*'Model inputs'!AA26 -> 263.63636 | F32: ='Model inputs'!F35*'Model inputs'!AA26 -> 345.45455 | G32: ='Model inputs'!G35*'Model inputs'!AA26 -> 427.27273 | H32: ='Model inputs'!H35*'Model inputs'!AA26 -> 509.09091 | I32: ='Model inputs'!I35*'Model inputs'!AA26 -> 590.90909 | J32: ='Model inputs'!J35*'Model inputs'!AA26 -> 672.72727 | K32: ='Model inputs'!K35*'Model inputs'!AA26 -> 754.54545 | L32: ='Model inputs'!L35*'Model inputs'!AA26 -> 836.36364 | M32: ='Model inputs'!M35*'Model inputs'!AA26 -> 918.18182 | N32: ='Model inputs'!N35*'Model inputs'!AA26 -> 1000 | O32: ='Model inputs'!O35*'Model inputs'!AA26 -> 1000 | P32: ='Model inputs'!P35*'Model inputs'!AA26 -> 1000 | Q32: ='Model inputs'!Q35*'Model inputs'!AA26 -> 1000 | R32: ='Model inputs'!R35*'Model inputs'!AA26 -> 1000 | S32: ='Model inputs'!S35*'Model inputs'!AA26 -> 1000 | T32: ='Model inputs'!T35*'Model inputs'!AA26 -> 1000 | U32: ='Model inputs'!U35*'Model inputs'!AA26 -> 1000 | V32: ='Model inputs'!V35*'Model inputs'!AA26 -> 1000 | W32: ='Model inputs'!W35*'Model inputs'!AA26 -> 1000 | X32: ='Model inputs'!X35*'Model inputs'!AA26 -> 1000 | Y32: ='Model inputs'!Y35*'Model inputs'!AA26 -> 1000 | Z32: ='Model inputs'!Z35*'Model inputs'!AA26 -> 1000 | AB32: 0 | AC32: 0 | AD32: 0 | AE32: 0 | AF32: 0 | AG32: 0 | AH32: 0 | AI32: 0
A33: Month number · Kedge P&L, Burn & Runway | B33: =IF('Model inputs'!B19="","",'Model inputs'!B19) -> 0 | C33: =IF('Model inputs'!C19="","",'Model inputs'!C19) -> 1 | D33: =IF('Model inputs'!D19="","",'Model inputs'!D19) -> 2 | E33: =IF('Model inputs'!E19="","",'Model inputs'!E19) -> 3 | F33: =IF('Model inputs'!F19="","",'Model inputs'!F19) -> 4 | G33: =IF('Model inputs'!G19="","",'Model inputs'!G19) -> 5 | H33: =IF('Model inputs'!H19="","",'Model inputs'!H19) -> 6 | I33: =IF('Model inputs'!I19="","",'Model inputs'!I19) -> 7 | ... Z33: =IF('Model inputs'!Z19="","",'Model inputs'!Z19) -> 24 | AB33: =0 -> 0 | AC33: =0 -> 0 | AD33: =0 -> 0 | AE33: =0 -> 0 | AF33: =0 -> 0 | AG33: =0 -> 0 | AH33: =0 -> 0 | AI33: =0 -> 0
A34: Starting cash · Cash balance | AA34: =0 -> 0
A35: Active teams · Funding needed to date | B35: =0 -> 0 | C35: =IF(IF(IF(ISERROR('Model inputs'!C19>='Model inputs'!AA36),'Model inputs'!C19>='Model inputs'!AA36,IF(OR('Model inputs'!C19="",'Model inputs'!AA36=""),"",'Model inputs'!C19>='Model inputs'!AA36))="",FALSE,IF(ISERROR('Model inputs'!C19>='Model inputs'!AA36),'Model inputs'!C19>='Model inputs'!AA36,IF(OR('Model inputs'!C19="",'Model inputs'!AA36=""),"",'Model inputs'!C19>='Model inputs'!AA36))),IF('Model inputs'!AA37="","",'Model inputs'!AA37),'Model inputs'!AA38+('Model inputs'!AA37-'Model inputs'!AA38)*('Model inputs'!C19-1)/('Model inputs'!AA36-1)) -> 5 | D35: =IF(IF(IF(ISERROR('Model inputs'!D19>='Model inputs'!AA36),'Model inputs'!D19>='Model inputs'!AA36,IF(OR('Model inputs'!D19="",'Model inputs'!AA36=""),"",'Model inputs'!D19>='Model inputs'!AA36))="",FALSE,IF(ISERROR('Model inputs'!D19>='Model inputs'!AA36),'Model inputs'!D19>='Model inputs'!AA36,IF(OR('Model inputs'!D19="",'Model inputs'!AA36=""),"",'Model inputs'!D19>='Model inputs'!AA36))),IF('Model inputs'!AA37="","",'Model inputs'!AA37),'Model inputs'!AA38+('Model inputs'!AA37-'Model inputs'!AA38)*('Model inputs'!D19-1)/('Model inputs'!AA36-1)) -> 9.0909091 | E35: =IF(IF(IF(ISERROR('Model inputs'!E19>='Model inputs'!AA36),'Model inputs'!E19>='Model inputs'!AA36,IF(OR('Model inputs'!E19="",'Model inputs'!AA36=""),"",'Model inputs'!E19>='Model inputs'!AA36))="",FALSE,IF(ISERROR('Model inputs'!E19>='Model inputs'!AA36),'Model inputs'!E19>='Model inputs'!AA36,IF(OR('Model inputs'!E19="",'Model inputs'!AA36=""),"",'Model inputs'!E19>='Model inputs'!AA36))),IF('Model inputs'!AA37="","",'Model inputs'!AA37),'Model inputs'!AA38+('Model inputs'!AA37-'Model inputs'!AA38)*('Model inputs'!E19-1)/('Model inputs'!AA36-1)) -> 13.181818 | F35: =IF(IF(IF(ISERROR('Model inputs'!F19>='Model inputs'!AA36),'Model inputs'!F19>='Model inputs'!AA36,IF(OR('Model inputs'!F19="",'Model inputs'!AA36=""),"",'Model inputs'!F19>='Model inputs'!AA36))="",FALSE,IF(ISERROR('Model inputs'!F19>='Model inputs'!AA36),'Model inputs'!F19>='Model inputs'!AA36,IF(OR('Model inputs'!F19="",'Model inputs'!AA36=""),"",'Model inputs'!F19>='Model inputs'!AA36))),IF('Model inputs'!AA37="","",'Model inputs'!AA37),'Model inputs'!AA38+('Model inputs'!AA37-'Model inputs'!AA38)*('Model inputs'!F19-1)/('Model inputs'!AA36-1)) -> 17.272727 | G35: =IF(IF(IF(ISERROR('Model inputs'!G19>='Model inputs'!AA36),'Model inputs'!G19>='Model inputs'!AA36,IF(OR('Model inputs'!G19="",'Model inputs'!AA36=""),"",'Model inputs'!G19>='Model inputs'!AA36))="",FALSE,IF(ISERROR('Model inputs'!G19>='Model inputs'!AA36),'Model inputs'!G19>='Model inputs'!AA36,IF(OR('Model inputs'!G19="",'Model inputs'!AA36=""),"",'Model inputs'!G19>='Model inputs'!AA36))),IF('Model inputs'!AA37="","",'Model inputs'!AA37),'Model inputs'!AA38+('Model inputs'!AA37-'Model inputs'!AA38)*('Model inputs'!G19-1)/('Model inputs'!AA36-1)) -> 21.363636 | H35: =IF(IF(IF(ISERROR('Model inputs'!H19>='Model inputs'!AA36),'Model inputs'!H19>='Model inputs'!AA36,IF(OR('Model inputs'!H19="",'Model inputs'!AA36=""),"",'Model inputs'!H19>='Model inputs'!AA36))="",FALSE,IF(ISERROR('Model inputs'!H19>='Model inputs'!AA36),'Model inputs'!H19>='Model inputs'!AA36,IF(OR('Model inputs'!H19="",'Model inputs'!AA36=""),"",'Model inputs'!H19>='Model inputs'!AA36))),IF('Model inputs'!AA37="","",'Model inputs'!AA37),'Model inputs'!AA38+('Model inputs'!AA37-'Model inputs'!AA38)*('Model inputs'!H19-1)/('Model inputs'!AA36-1)) -> 25.454545 | I35: =IF(IF(IF(ISERROR('Model inputs'!I19>='Model inputs'!AA36),'Model inputs'!I19>='Model inputs'!AA36,IF(OR('Model inputs'!I19="",'Model inputs'!AA36=""),"",'Model inputs'!I19>='Model inputs'!AA36))="",FALSE,IF(ISERROR('Model inputs'!I19>='Model inputs'!AA36),'Model inputs'!I19>='Model inputs'!AA36,IF(OR('Model inputs'!I19="",'Model inputs'!AA36=""),"",'Model inputs'!I19>='Model inputs'!AA36))),IF('Model inputs'!AA37="","",'Model inputs'!AA37),'Model inputs'!AA38+('Model inputs'!AA37-'Model inputs'!AA38)*('Model inputs'!I19-1)/('Model inputs'!AA36-1)) -> 29.545455 | J35: =IF(IF(IF(ISERROR('Model inputs'!J19>='Model inputs'!AA36),'Model inputs'!J19>='Model inputs'!AA36,IF(OR('Model inputs'!J19="",'Model inputs'!AA36=""),"",'Model inputs'!J19>='Model inputs'!AA36))="",FALSE,IF(ISERROR('Model inputs'!J19>='Model inputs'!AA36),'Model inputs'!J19>='Model inputs'!AA36,IF(OR('Model inputs'!J19="",'Model inputs'!AA36=""),"",'Model inputs'!J19>='Model inputs'!AA36))),IF('Model inputs'!AA37="","",'Model inputs'!AA37),'Model inputs'!AA38+('Model inputs'!AA37-'Model inputs'!AA38)*('Model inputs'!J19-1)/('Model inputs'!AA36-1)) -> 33.636364 | K35: =IF(IF(IF(ISERROR('Model inputs'!K19>='Model inputs'!AA36),'Model inputs'!K19>='Model inputs'!AA36,IF(OR('Model inputs'!K19="",'Model inputs'!AA36=""),"",'Model inputs'!K19>='Model inputs'!AA36))="",FALSE,IF(ISERROR('Model inputs'!K19>='Model inputs'!AA36),'Model inputs'!K19>='Model inputs'!AA36,IF(OR('Model inputs'!K19="",'Model inputs'!AA36=""),"",'Model inputs'!K19>='Model inputs'!AA36))),IF('Model inputs'!AA37="","",'Model inputs'!AA37),'Model inputs'!AA38+('Model inputs'!AA37-'Model inputs'!AA38)*('Model inputs'!K19-1)/('Model inputs'!AA36-1)) -> 37.727273 | L35: =IF(IF(IF(ISERROR('Model inputs'!L19>='Model inputs'!AA36),'Model inputs'!L19>='Model inputs'!AA36,IF(OR('Model inputs'!L19="",'Model inputs'!AA36=""),"",'Model inputs'!L19>='Model inputs'!AA36))="",FALSE,IF(ISERROR('Model inputs'!L19>='Model inputs'!AA36),'Model inputs'!L19>='Model inputs'!AA36,IF(OR('Model inputs'!L19="",'Model inputs'!AA36=""),"",'Model inputs'!L19>='Model inputs'!AA36))),IF('Model inputs'!AA37="","",'Model inputs'!AA37),'Model inputs'!AA38+('Model inputs'!AA37-'Model inputs'!AA38)*('Model inputs'!L19-1)/('Model inputs'!AA36-1)) -> 41.818182 | M35: =IF(IF(IF(ISERROR('Model inputs'!M19>='Model inputs'!AA36),'Model inputs'!M19>='Model inputs'!AA36,IF(OR('Model inputs'!M19="",'Model inputs'!AA36=""),"",'Model inputs'!M19>='Model inputs'!AA36))="",FALSE,IF(ISERROR('Model inputs'!M19>='Model inputs'!AA36),'Model inputs'!M19>='Model inputs'!AA36,IF(OR('Model inputs'!M19="",'Model inputs'!AA36=""),"",'Model inputs'!M19>='Model inputs'!AA36))),IF('Model inputs'!AA37="","",'Model inputs'!AA37),'Model inputs'!AA38+('Model inputs'!AA37-'Model inputs'!AA38)*('Model inputs'!M19-1)/('Model inputs'!AA36-1)) -> 45.909091 | N35: =IF(IF(IF(ISERROR('Model inputs'!N19>='Model inputs'!AA36),'Model inputs'!N19>='Model inputs'!AA36,IF(OR('Model inputs'!N19="",'Model inputs'!AA36=""),"",'Model inputs'!N19>='Model inputs'!AA36))="",FALSE,IF(ISERROR('Model inputs'!N19>='Model inputs'!AA36),'Model inputs'!N19>='Model inputs'!AA36,IF(OR('Model inputs'!N19="",'Model inputs'!AA36=""),"",'Model inputs'!N19>='Model inputs'!AA36))),IF('Model inputs'!AA37="","",'Model inputs'!AA37),'Model inputs'!AA38+('Model inputs'!AA37-'Model inputs'!AA38)*('Model inputs'!N19-1)/('Model inputs'!AA36-1)) -> 50 | O35: =IF(IF(IF(ISERROR('Model inputs'!O19>='Model inputs'!AA36),'Model inputs'!O19>='Model inputs'!AA36,IF(OR('Model inputs'!O19="",'Model inputs'!AA36=""),"",'Model inputs'!O19>='Model inputs'!AA36))="",FALSE,IF(ISERROR('Model inputs'!O19>='Model inputs'!AA36),'Model inputs'!O19>='Model inputs'!AA36,IF(OR('Model inputs'!O19="",'Model inputs'!AA36=""),"",'Model inputs'!O19>='Model inputs'!AA36))),IF('Model inputs'!AA37="","",'Model inputs'!AA37),'Model inputs'!AA38+('Model inputs'!AA37-'Model inputs'!AA38)*('Model inputs'!O19-1)/('Model inputs'!AA36-1)) -> 50 | P35: =IF(IF(IF(ISERROR('Model inputs'!P19>='Model inputs'!AA36),'Model inputs'!P19>='Model inputs'!AA36,IF(OR('Model inputs'!P19="",'Model inputs'!AA36=""),"",'Model inputs'!P19>='Model inputs'!AA36))="",FALSE,IF(ISERROR('Model inputs'!P19>='Model inputs'!AA36),'Model inputs'!P19>='Model inputs'!AA36,IF(OR('Model inputs'!P19="",'Model inputs'!AA36=""),"",'Model inputs'!P19>='Model inputs'!AA36))),IF('Model inputs'!AA37="","",'Model inputs'!AA37),'Model inputs'!AA38+('Model inputs'!AA37-'Model inputs'!AA38)*('Model inputs'!P19-1)/('Model inputs'!AA36-1)) -> 50 | Q35: =IF(IF(IF(ISERROR('Model inputs'!Q19>='Model inputs'!AA36),'Model inputs'!Q19>='Model inputs'!AA36,IF(OR('Model inputs'!Q19="",'Model inputs'!AA36=""),"",'Model inputs'!Q19>='Model inputs'!AA36))="",FALSE,IF(ISERROR('Model inputs'!Q19>='Model inputs'!AA36),'Model inputs'!Q19>='Model inputs'!AA36,IF(OR('Model inputs'!Q19="",'Model inputs'!AA36=""),"",'Model inputs'!Q19>='Model inputs'!AA36))),IF('Model inputs'!AA37="","",'Model inputs'!AA37),'Model inputs'!AA38+('Model inputs'!AA37-'Model inputs'!AA38)*('Model inputs'!Q19-1)/('Model inputs'!AA36-1)) -> 50 | R35: =IF(IF(IF(ISERROR('Model inputs'!R19>='Model inputs'!AA36),'Model inputs'!R19>='Model inputs'!AA36,IF(OR('Model inputs'!R19="",'Model inputs'!AA36=""),"",'Model inputs'!R19>='Model inputs'!AA36))="",FALSE,IF(ISERROR('Model inputs'!R19>='Model inputs'!AA36),'Model inputs'!R19>='Model inputs'!AA36,IF(OR('Model inputs'!R19="",'Model inputs'!AA36=""),"",'Model inputs'!R19>='Model inputs'!AA36))),IF('Model inputs'!AA37="","",'Model inputs'!AA37),'Model inputs'!AA38+('Model inputs'!AA37-'Model inputs'!AA38)*('Model inputs'!R19-1)/('Model inputs'!AA36-1)) -> 50 | S35: =IF(IF(IF(ISERROR('Model inputs'!S19>='Model inputs'!AA36),'Model inputs'!S19>='Model inputs'!AA36,IF(OR('Model inputs'!S19="",'Model inputs'!AA36=""),"",'Model inputs'!S19>='Model inputs'!AA36))="",FALSE,IF(ISERROR('Model inputs'!S19>='Model inputs'!AA36),'Model inputs'!S19>='Model inputs'!AA36,IF(OR('Model inputs'!S19="",'Model inputs'!AA36=""),"",'Model inputs'!S19>='Model inputs'!AA36))),IF('Model inputs'!AA37="","",'Model inputs'!AA37),'Model inputs'!AA38+('Model inputs'!AA37-'Model inputs'!AA38)*('Model inputs'!S19-1)/('Model inputs'!AA36-1)) -> 50 | T35: =IF(IF(IF(ISERROR('Model inputs'!T19>='Model inputs'!AA36),'Model inputs'!T19>='Model inputs'!AA36,IF(OR('Model inputs'!T19="",'Model inputs'!AA36=""),"",'Model inputs'!T19>='Model inputs'!AA36))="",FALSE,IF(ISERROR('Model inputs'!T19>='Model inputs'!AA36),'Model inputs'!T19>='Model inputs'!AA36,IF(OR('Model inputs'!T19="",'Model inputs'!AA36=""),"",'Model inputs'!T19>='Model inputs'!AA36))),IF('Model inputs'!AA37="","",'Model inputs'!AA37),'Model inputs'!AA38+('Model inputs'!AA37-'Model inputs'!AA38)*('Model inputs'!T19-1)/('Model inputs'!AA36-1)) -> 50 | U35: =IF(IF(IF(ISERROR('Model inputs'!U19>='Model inputs'!AA36),'Model inputs'!U19>='Model inputs'!AA36,IF(OR('Model inputs'!U19="",'Model inputs'!AA36=""),"",'Model inputs'!U19>='Model inputs'!AA36))="",FALSE,IF(ISERROR('Model inputs'!U19>='Model inputs'!AA36),'Model inputs'!U19>='Model inputs'!AA36,IF(OR('Model inputs'!U19="",'Model inputs'!AA36=""),"",'Model inputs'!U19>='Model inputs'!AA36))),IF('Model inputs'!AA37="","",'Model inputs'!AA37),'Model inputs'!AA38+('Model inputs'!AA37-'Model inputs'!AA38)*('Model inputs'!U19-1)/('Model inputs'!AA36-1)) -> 50 | V35: =IF(IF(IF(ISERROR('Model inputs'!V19>='Model inputs'!AA36),'Model inputs'!V19>='Model inputs'!AA36,IF(OR('Model inputs'!V19="",'Model inputs'!AA36=""),"",'Model inputs'!V19>='Model inputs'!AA36))="",FALSE,IF(ISERROR('Model inputs'!V19>='Model inputs'!AA36),'Model inputs'!V19>='Model inputs'!AA36,IF(OR('Model inputs'!V19="",'Model inputs'!AA36=""),"",'Model inputs'!V19>='Model inputs'!AA36))),IF('Model inputs'!AA37="","",'Model inputs'!AA37),'Model inputs'!AA38+('Model inputs'!AA37-'Model inputs'!AA38)*('Model inputs'!V19-1)/('Model inputs'!AA36-1)) -> 50 | W35: =IF(IF(IF(ISERROR('Model inputs'!W19>='Model inputs'!AA36),'Model inputs'!W19>='Model inputs'!AA36,IF(OR('Model inputs'!W19="",'Model inputs'!AA36=""),"",'Model inputs'!W19>='Model inputs'!AA36))="",FALSE,IF(ISERROR('Model inputs'!W19>='Model inputs'!AA36),'Model inputs'!W19>='Model inputs'!AA36,IF(OR('Model inputs'!W19="",'Model inputs'!AA36=""),"",'Model inputs'!W19>='Model inputs'!AA36))),IF('Model inputs'!AA37="","",'Model inputs'!AA37),'Model inputs'!AA38+('Model inputs'!AA37-'Model inputs'!AA38)*('Model inputs'!W19-1)/('Model inputs'!AA36-1)) -> 50 | X35: =IF(IF(IF(ISERROR('Model inputs'!X19>='Model inputs'!AA36),'Model inputs'!X19>='Model inputs'!AA36,IF(OR('Model inputs'!X19="",'Model inputs'!AA36=""),"",'Model inputs'!X19>='Model inputs'!AA36))="",FALSE,IF(ISERROR('Model inputs'!X19>='Model inputs'!AA36),'Model inputs'!X19>='Model inputs'!AA36,IF(OR('Model inputs'!X19="",'Model inputs'!AA36=""),"",'Model inputs'!X19>='Model inputs'!AA36))),IF('Model inputs'!AA37="","",'Model inputs'!AA37),'Model inputs'!AA38+('Model inputs'!AA37-'Model inputs'!AA38)*('Model inputs'!X19-1)/('Model inputs'!AA36-1)) -> 50 | Y35: =IF(IF(IF(ISERROR('Model inputs'!Y19>='Model inputs'!AA36),'Model inputs'!Y19>='Model inputs'!AA36,IF(OR('Model inputs'!Y19="",'Model inputs'!AA36=""),"",'Model inputs'!Y19>='Model inputs'!AA36))="",FALSE,IF(ISERROR('Model inputs'!Y19>='Model inputs'!AA36),'Model inputs'!Y19>='Model inputs'!AA36,IF(OR('Model inputs'!Y19="",'Model inputs'!AA36=""),"",'Model inputs'!Y19>='Model inputs'!AA36))),IF('Model inputs'!AA37="","",'Model inputs'!AA37),'Model inputs'!AA38+('Model inputs'!AA37-'Model inputs'!AA38)*('Model inputs'!Y19-1)/('Model inputs'!AA36-1)) -> 50 | Z35: =IF(IF(IF(ISERROR('Model inputs'!Z19>='Model inputs'!AA36),'Model inputs'!Z19>='Model inputs'!AA36,IF(OR('Model inputs'!Z19="",'Model inputs'!AA36=""),"",'Model inputs'!Z19>='Model inputs'!AA36))="",FALSE,IF(ISERROR('Model inputs'!Z19>='Model inputs'!AA36),'Model inputs'!Z19>='Model inputs'!AA36,IF(OR('Model inputs'!Z19="",'Model inputs'!AA36=""),"",'Model inputs'!Z19>='Model inputs'!AA36))),IF('Model inputs'!AA37="","",'Model inputs'!AA37),'Model inputs'!AA38+('Model inputs'!AA37-'Model inputs'!AA38)*('Model inputs'!Z19-1)/('Model inputs'!AA36-1)) -> 50 | AB35: =0 -> 0 | AC35: =0 -> 0 | AD35: =0 -> 0 | AE35: =0 -> 0 | AF35: =0 -> 0 | AG35: =0 -> 0 | AH35: =0 -> 0 | AI35: =0 -> 0
A36: Months to full ramp · Active teams · Funding needed to date | AA36: =12 -> 12
A37: Teams at full ramp · Active teams · Funding needed to date | AA37: =50 -> 50
A38: Teams at launch · Active teams · Funding needed to date | AA38: =5 -> 5
